{
    "player_name": "Isaiah Jackson",
    "player_code": "05uiw",
    "league_id": "ifa1anexmdgtlk9s",
    "data": [
        {
            "Date": "Nov 8",
            "Team": "IND",
            "Opp": "@DEN",
            "Score": "L 100-117",
            "FPts": 32,
            "MIN": "18:30",
            "FGM": 1,
            "FGA": 5,
            "FG%": 0.2,
            "3PTM": 0,
            "3PTA": 0,
            "3PT%": NaN,
            "FTM": 2,
            "FTA": 4,
            "FT%": 0.5,
            "REB": 6,
            "AST": 1,
            "ST": 3,
            "BLK": 0,
            "TO": 0,
            "PF": 2,
            "PTS": 4
        },
        {
            "Date": "Nov 5",
            "Team": "IND",
            "Opp": "BKN",
            "Score": "L 103-112",
            "FPts": 26,
            "MIN": "20:26",
            "FGM": 4,
            "FGA": 6,
            "FG%": 0.667,
            "3PTM": 0,
            "3PTA": 0,
            "3PT%": NaN,
            "FTM": 0,
            "FTA": 0,
            "FT%": NaN,
            "REB": 7,
            "AST": 1,
            "ST": 1,
            "BLK": 0,
            "TO": 2,
            "PF": 4,
            "PTS": 8
        },
        {
            "Date": "Nov 3",
            "Team": "IND",
            "Opp": "MIL",
            "Score": "L 115-117",
            "FPts": 78,
            "MIN": "29:20",
            "FGM": 8,
            "FGA": 12,
            "FG%": 0.667,
            "3PTM": 0,
            "3PTA": 0,
            "3PT%": NaN,
            "FTM": 5,
            "FTA": 6,
            "FT%": 0.833,
            "REB": 10,
            "AST": 1,
            "ST": 2,
            "BLK": 1,
            "TO": 1,
            "PF": 3,
            "PTS": 21
        },
        {
            "Date": "Nov 1",
            "Team": "IND",
            "Opp": "GS",
            "Score": "W 114-109",
            "FPts": 39,
            "MIN": "20:57",
            "FGM": 2,
            "FGA": 5,
            "FG%": 0.4,
            "3PTM": 0,
            "3PTA": 0,
            "3PT%": NaN,
            "FTM": 6,
            "FTA": 6,
            "FT%": 1.0,
            "REB": 8,
            "AST": 1,
            "ST": 0,
            "BLK": 1,
            "TO": 0,
            "PF": 3,
            "PTS": 10
        },
        {
            "Date": "Oct 31",
            "Team": "IND",
            "Opp": "ATL",
            "Score": "L 108-128",
            "FPts": 44,
            "MIN": "27:03",
            "FGM": 4,
            "FGA": 7,
            "FG%": 0.571,
            "3PTM": 0,
            "3PTA": 0,
            "3PT%": NaN,
            "FTM": 1,
            "FTA": 2,
            "FT%": 0.5,
            "REB": 11,
            "AST": 2,
            "ST": 0,
            "BLK": 0,
            "TO": 0,
            "PF": 3,
            "PTS": 9
        },
        {
            "Date": "Oct 29",
            "Team": "IND",
            "Opp": "@DAL",
            "Score": "L 105-107",
            "FPts": 7,
            "MIN": "11:24",
            "FGM": 3,
            "FGA": 5,
            "FG%": 0.6,
            "3PTM": 0,
            "3PTA": 0,
            "3PT%": NaN,
            "FTM": 0,
            "FTA": 0,
            "FT%": NaN,
            "REB": 2,
            "AST": 0,
            "ST": 0,
            "BLK": 0,
            "TO": 3,
            "PF": 4,
            "PTS": 6
        },
        {
            "Date": "Oct 26",
            "Team": "IND",
            "Opp": "@MIN",
            "Score": "L 110-114",
            "FPts": 18,
            "MIN": "14:38",
            "FGM": 2,
            "FGA": 4,
            "FG%": 0.5,
            "3PTM": 0,
            "3PTA": 0,
            "3PT%": NaN,
            "FTM": 2,
            "FTA": 2,
            "FT%": 1.0,
            "REB": 3,
            "AST": 2,
            "ST": 0,
            "BLK": 0,
            "TO": 2,
            "PF": 5,
            "PTS": 6
        },
        {
            "Date": "Oct 25",
            "Team": "IND",
            "Opp": "@MEM",
            "Score": "L 103-128",
            "FPts": 17,
            "MIN": "11:59",
            "FGM": 1,
            "FGA": 4,
            "FG%": 0.25,
            "3PTM": 0,
            "3PTA": 0,
            "3PT%": NaN,
            "FTM": 1,
            "FTA": 1,
            "FT%": 1.0,
            "REB": 5,
            "AST": 0,
            "ST": 0,
            "BLK": 1,
            "TO": 0,
            "PF": 1,
            "PTS": 3
        },
        {
            "Date": "Oct 23",
            "Team": "IND",
            "Opp": "OKC",
            "Score": "L 135-141",
            "FPts": -5,
            "MIN": "08:29",
            "FGM": 0,
            "FGA": 2,
            "FG%": 0.0,
            "3PTM": 0,
            "3PTA": 0,
            "3PT%": NaN,
            "FTM": 0,
            "FTA": 0,
            "FT%": NaN,
            "REB": 1,
            "AST": 0,
            "ST": 0,
            "BLK": 0,
            "TO": 2,
            "PF": 4,
            "PTS": 0
        }
    ]
}