{
    "player_name": "Jarrett Allen",
    "player_code": "04ewm",
    "league_id": "ifa1anexmdgtlk9s",
    "season": "2020-21",
    "data": [
        {
            "Date": "May 16",
            "Team": "CLE",
            "Opp": "@BKN",
            "Score": "L 109-123",
            "FPts": 40,
            "FG-": "5.0",
            "3PTM": 0,
            "FT-": "2",
            "PTS": 9,
            "OREB": "2",
            "REB": 11,
            "AST": 0,
            "ST": 1,
            "BLK": 1,
            "TO": 0,
            "TF": "0",
            "EJ": "0",
            "3D": "0",
            "2D": "0"
        },
        {
            "Date": "May 14",
            "Team": "CLE",
            "Opp": "@WAS",
            "Score": "L 105-120",
            "FPts": 68,
            "FG-": "5.0",
            "3PTM": 0,
            "FT-": "2",
            "PTS": 18,
            "OREB": "3",
            "REB": 14,
            "AST": 3,
            "ST": 0,
            "BLK": 1,
            "TO": 2,
            "TF": "0",
            "EJ": "0",
            "3D": "0",
            "2D": "1"
        },
        {
            "Date": "May 12",
            "Team": "CLE",
            "Opp": "BOS",
            "Score": "W 102-94",
            "FPts": 31,
            "FG-": "6.0",
            "3PTM": 0,
            "FT-": "0",
            "PTS": 8,
            "OREB": "3",
            "REB": 10,
            "AST": 2,
            "ST": 0,
            "BLK": 1,
            "TO": 3,
            "TF": "0",
            "EJ": "0",
            "3D": "0",
            "2D": "0"
        },
        {
            "Date": "May 10",
            "Team": "CLE",
            "Opp": "IND",
            "Score": "L 102-111",
            "FPts": 54,
            "FG-": "2.0",
            "3PTM": 1,
            "FT-": "1",
            "PTS": 12,
            "OREB": "5",
            "REB": 9,
            "AST": 3,
            "ST": 0,
            "BLK": 1,
            "TO": 2,
            "TF": "0",
            "EJ": "0",
            "3D": "0",
            "2D": "0"
        },
        {
            "Date": "May 9",
            "Team": "CLE",
            "Opp": "DAL",
            "Score": "L 97-124",
            "FPts": 14,
            "FG-": "3.0",
            "3PTM": 0,
            "FT-": "3",
            "PTS": 5,
            "OREB": "2",
            "REB": 5,
            "AST": 1,
            "ST": 0,
            "BLK": 0,
            "TO": 1,
            "TF": "0",
            "EJ": "0",
            "3D": "0",
            "2D": "0"
        },
        {
            "Date": "May 7",
            "Team": "CLE",
            "Opp": "@DAL",
            "Score": "L 90-110",
            "FPts": 38,
            "FG-": "4.0",
            "3PTM": 0,
            "FT-": "1",
            "PTS": 5,
            "OREB": "4",
            "REB": 12,
            "AST": 1,
            "ST": 2,
            "BLK": 0,
            "TO": 3,
            "TF": "0",
            "EJ": "0",
            "3D": "0",
            "2D": "0"
        },
        {
            "Date": "May 5",
            "Team": "CLE",
            "Opp": "POR",
            "Score": "L 105-141",
            "FPts": 50,
            "FG-": "5.0",
            "3PTM": 0,
            "FT-": "1",
            "PTS": 9,
            "OREB": "5",
            "REB": 13,
            "AST": 2,
            "ST": 1,
            "BLK": 1,
            "TO": 2,
            "TF": "0",
            "EJ": "0",
            "3D": "0",
            "2D": "0"
        },
        {
            "Date": "May 4",
            "Team": "CLE",
            "Opp": "PHO",
            "Score": "L 118-134",
            "FPts": 65,
            "FG-": "4.0",
            "3PTM": 0,
            "FT-": "2",
            "PTS": 17,
            "OREB": "4",
            "REB": 8,
            "AST": 5,
            "ST": 1,
            "BLK": 1,
            "TO": 2,
            "TF": "0",
            "EJ": "0",
            "3D": "0",
            "2D": "0"
        },
        {
            "Date": "May 1",
            "Team": "CLE",
            "Opp": "MIA",
            "Score": "L 107-124",
            "FPts": 45,
            "FG-": "1.0",
            "3PTM": 0,
            "FT-": "0",
            "PTS": 6,
            "OREB": "3",
            "REB": 14,
            "AST": 2,
            "ST": 0,
            "BLK": 1,
            "TO": 3,
            "TF": "0",
            "EJ": "0",
            "3D": "0",
            "2D": "0"
        },
        {
            "Date": "Apr 30",
            "Team": "CLE",
            "Opp": "WAS",
            "Score": "L 93-122",
            "FPts": 53,
            "FG-": "3.0",
            "3PTM": 0,
            "FT-": "2",
            "PTS": 13,
            "OREB": "3",
            "REB": 11,
            "AST": 2,
            "ST": 0,
            "BLK": 1,
            "TO": 2,
            "TF": "0",
            "EJ": "0",
            "3D": "0",
            "2D": "1"
        },
        {
            "Date": "Apr 28",
            "Team": "CLE",
            "Opp": "ORL",
            "Score": "L 104-109",
            "FPts": 74,
            "FG-": "5.0",
            "3PTM": 0,
            "FT-": "3",
            "PTS": 17,
            "OREB": "6",
            "REB": 13,
            "AST": 1,
            "ST": 1,
            "BLK": 2,
            "TO": 0,
            "TF": "0",
            "EJ": "0",
            "3D": "0",
            "2D": "1"
        },
        {
            "Date": "Apr 26",
            "Team": "CLE",
            "Opp": "@TOR",
            "Score": "L 96-112",
            "FPts": 46,
            "FG-": "4.0",
            "3PTM": 0,
            "FT-": "0",
            "PTS": 15,
            "OREB": "2",
            "REB": 7,
            "AST": 2,
            "ST": 1,
            "BLK": 0,
            "TO": 2,
            "TF": "0",
            "EJ": "0",
            "3D": "0",
            "2D": "0"
        },
        {
            "Date": "Apr 25",
            "Team": "CLE",
            "Opp": "@WAS",
            "Score": "L 110-119",
            "FPts": 107,
            "FG-": "2.0",
            "3PTM": 0,
            "FT-": "2",
            "PTS": 27,
            "OREB": "7",
            "REB": 12,
            "AST": 2,
            "ST": 2,
            "BLK": 3,
            "TO": 3,
            "TF": "0",
            "EJ": "0",
            "3D": "0",
            "2D": "1"
        },
        {
            "Date": "Apr 23",
            "Team": "CLE",
            "Opp": "@CHA",
            "Score": "L 102-108",
            "FPts": 49,
            "FG-": "0.0",
            "3PTM": 0,
            "FT-": "1",
            "PTS": 15,
            "OREB": "3",
            "REB": 9,
            "AST": 1,
            "ST": 0,
            "BLK": 0,
            "TO": 2,
            "TF": "0",
            "EJ": "0",
            "3D": "0",
            "2D": "0"
        },
        {
            "Date": "Apr 21",
            "Team": "CLE",
            "Opp": "CHI",
            "Score": "W 121-105",
            "FPts": 35,
            "FG-": "2.0",
            "3PTM": 0,
            "FT-": "0",
            "PTS": 8,
            "OREB": "1",
            "REB": 9,
            "AST": 0,
            "ST": 0,
            "BLK": 1,
            "TO": 0,
            "TF": "0",
            "EJ": "0",
            "3D": "0",
            "2D": "0"
        },
        {
            "Date": "Apr 19",
            "Team": "CLE",
            "Opp": "@DET",
            "Score": "L 105-109",
            "FPts": 21,
            "FG-": "2.0",
            "3PTM": 0,
            "FT-": "0",
            "PTS": 5,
            "OREB": "1",
            "REB": 5,
            "AST": 0,
            "ST": 1,
            "BLK": 1,
            "TO": 3,
            "TF": "0",
            "EJ": "0",
            "3D": "0",
            "2D": "0"
        },
        {
            "Date": "Apr 17",
            "Team": "CLE",
            "Opp": "@CHI",
            "Score": "L 96-106",
            "FPts": 46,
            "FG-": "5.0",
            "3PTM": 0,
            "FT-": "0",
            "PTS": 10,
            "OREB": "4",
            "REB": 11,
            "AST": 2,
            "ST": 0,
            "BLK": 0,
            "TO": 0,
            "TF": "0",
            "EJ": "0",
            "3D": "0",
            "2D": "1"
        },
        {
            "Date": "Apr 15",
            "Team": "CLE",
            "Opp": "GS",
            "Score": "L 101-119",
            "FPts": 70,
            "FG-": "1.0",
            "3PTM": 0,
            "FT-": "1",
            "PTS": 17,
            "OREB": "2",
            "REB": 14,
            "AST": 1,
            "ST": 2,
            "BLK": 0,
            "TO": 5,
            "TF": "0",
            "EJ": "0",
            "3D": "0",
            "2D": "1"
        },
        {
            "Date": "Apr 14",
            "Team": "CLE",
            "Opp": "@CHA",
            "Score": "W 103-90",
            "FPts": 49,
            "FG-": "4.0",
            "3PTM": 0,
            "FT-": "1",
            "PTS": 15,
            "OREB": "2",
            "REB": 8,
            "AST": 2,
            "ST": 0,
            "BLK": 1,
            "TO": 0,
            "TF": "0",
            "EJ": "0",
            "3D": "0",
            "2D": "0"
        },
        {
            "Date": "Mar 26",
            "Team": "CLE",
            "Opp": "@LAL",
            "Score": "L 86-100",
            "FPts": 68,
            "FG-": "6.0",
            "3PTM": 1,
            "FT-": "4",
            "PTS": 13,
            "OREB": "4",
            "REB": 11,
            "AST": 5,
            "ST": 1,
            "BLK": 1,
            "TO": 0,
            "TF": "0",
            "EJ": "0",
            "3D": "0",
            "2D": "1"
        },
        {
            "Date": "Mar 24",
            "Team": "CLE",
            "Opp": "@CHI",
            "Score": "W 103-94",
            "FPts": 73,
            "FG-": "3.0",
            "3PTM": 0,
            "FT-": "1",
            "PTS": 19,
            "OREB": "3",
            "REB": 9,
            "AST": 1,
            "ST": 2,
            "BLK": 3,
            "TO": 3,
            "TF": "0",
            "EJ": "0",
            "3D": "0",
            "2D": "0"
        },
        {
            "Date": "Mar 22",
            "Team": "CLE",
            "Opp": "SAC",
            "Score": "L 105-119",
            "FPts": 28,
            "FG-": "7.0",
            "3PTM": 0,
            "FT-": "2",
            "PTS": 11,
            "OREB": "2",
            "REB": 9,
            "AST": 0,
            "ST": 0,
            "BLK": 1,
            "TO": 1,
            "TF": "0",
            "EJ": "0",
            "3D": "0",
            "2D": "0"
        },
        {
            "Date": "Mar 21",
            "Team": "CLE",
            "Opp": "TOR",
            "Score": "W 116-105",
            "FPts": 60,
            "FG-": "4.0",
            "3PTM": 0,
            "FT-": "2",
            "PTS": 17,
            "OREB": "1",
            "REB": 15,
            "AST": 1,
            "ST": 0,
            "BLK": 1,
            "TO": 3,
            "TF": "0",
            "EJ": "0",
            "3D": "0",
            "2D": "1"
        },
        {
            "Date": "Mar 19",
            "Team": "CLE",
            "Opp": "SA",
            "Score": "L 110-116",
            "FPts": 64,
            "FG-": "2.0",
            "3PTM": 0,
            "FT-": "1",
            "PTS": 15,
            "OREB": "3",
            "REB": 11,
            "AST": 2,
            "ST": 0,
            "BLK": 2,
            "TO": 2,
            "TF": "0",
            "EJ": "0",
            "3D": "0",
            "2D": "1"
        },
        {
            "Date": "Mar 17",
            "Team": "CLE",
            "Opp": "BOS",
            "Score": "W 117-110",
            "FPts": 24,
            "FG-": "4.0",
            "3PTM": 0,
            "FT-": "3",
            "PTS": 7,
            "OREB": "2",
            "REB": 7,
            "AST": 1,
            "ST": 0,
            "BLK": 1,
            "TO": 1,
            "TF": "0",
            "EJ": "0",
            "3D": "0",
            "2D": "0"
        },
        {
            "Date": "Mar 16",
            "Team": "CLE",
            "Opp": "@MIA",
            "Score": "L 98-113",
            "FPts": 45,
            "FG-": "4.0",
            "3PTM": 0,
            "FT-": "0",
            "PTS": 8,
            "OREB": "3",
            "REB": 10,
            "AST": 2,
            "ST": 0,
            "BLK": 2,
            "TO": 0,
            "TF": "0",
            "EJ": "0",
            "3D": "0",
            "2D": "0"
        },
        {
            "Date": "Mar 14",
            "Team": "CLE",
            "Opp": "@ATL",
            "Score": "L 82-100",
            "FPts": 37,
            "FG-": "2.0",
            "3PTM": 0,
            "FT-": "7",
            "PTS": 9,
            "OREB": "4",
            "REB": 11,
            "AST": 0,
            "ST": 0,
            "BLK": 1,
            "TO": 0,
            "TF": "0",
            "EJ": "0",
            "3D": "0",
            "2D": "0"
        },
        {
            "Date": "Mar 12",
            "Team": "CLE",
            "Opp": "@NO",
            "Score": "L 82-116",
            "FPts": 38,
            "FG-": "4.0",
            "3PTM": 0,
            "FT-": "1",
            "PTS": 5,
            "OREB": "1",
            "REB": 7,
            "AST": 2,
            "ST": 1,
            "BLK": 3,
            "TO": 1,
            "TF": "0",
            "EJ": "0",
            "3D": "0",
            "2D": "0"
        },
        {
            "Date": "Mar 3",
            "Team": "CLE",
            "Opp": "IND",
            "Score": "L 111-114",
            "FPts": 62,
            "FG-": "1.0",
            "3PTM": 0,
            "FT-": "0",
            "PTS": 17,
            "OREB": "3",
            "REB": 11,
            "AST": 1,
            "ST": 0,
            "BLK": 0,
            "TO": 1,
            "TF": "0",
            "EJ": "0",
            "3D": "0",
            "2D": "1"
        },
        {
            "Date": "Mar 1",
            "Team": "CLE",
            "Opp": "@HOU",
            "Score": "W 101-90",
            "FPts": 49,
            "FG-": "2.0",
            "3PTM": 0,
            "FT-": "0",
            "PTS": 10,
            "OREB": "2",
            "REB": 15,
            "AST": 1,
            "ST": 0,
            "BLK": 1,
            "TO": 2,
            "TF": "1",
            "EJ": "0",
            "3D": "0",
            "2D": "1"
        },
        {
            "Date": "Feb 27",
            "Team": "CLE",
            "Opp": "@PHI",
            "Score": "W 112-109",
            "FPts": 48,
            "FG-": "6.0",
            "3PTM": 1,
            "FT-": "1",
            "PTS": 14,
            "OREB": "3",
            "REB": 9,
            "AST": 3,
            "ST": 1,
            "BLK": 0,
            "TO": 3,
            "TF": "0",
            "EJ": "0",
            "3D": "0",
            "2D": "0"
        },
        {
            "Date": "Feb 24",
            "Team": "CLE",
            "Opp": "HOU",
            "Score": "W 112-96",
            "FPts": 116,
            "FG-": "1.0",
            "3PTM": 1,
            "FT-": "3",
            "PTS": 26,
            "OREB": "6",
            "REB": 18,
            "AST": 2,
            "ST": 0,
            "BLK": 4,
            "TO": 1,
            "TF": "0",
            "EJ": "0",
            "3D": "0",
            "2D": "1"
        },
        {
            "Date": "Feb 23",
            "Team": "CLE",
            "Opp": "ATL",
            "Score": "W 112-111",
            "FPts": 79,
            "FG-": "6.0",
            "3PTM": 1,
            "FT-": "0",
            "PTS": 13,
            "OREB": "2",
            "REB": 14,
            "AST": 2,
            "ST": 1,
            "BLK": 4,
            "TO": 0,
            "TF": "0",
            "EJ": "0",
            "3D": "0",
            "2D": "1"
        },
        {
            "Date": "Feb 21",
            "Team": "CLE",
            "Opp": "OKC",
            "Score": "L 101-117",
            "FPts": 108,
            "FG-": "0.0",
            "3PTM": 0,
            "FT-": "3",
            "PTS": 26,
            "OREB": "9",
            "REB": 17,
            "AST": 2,
            "ST": 0,
            "BLK": 3,
            "TO": 3,
            "TF": "0",
            "EJ": "0",
            "3D": "0",
            "2D": "1"
        },
        {
            "Date": "Feb 19",
            "Team": "CLE",
            "Opp": "DEN",
            "Score": "L 103-120",
            "FPts": 82,
            "FG-": "1.0",
            "3PTM": 0,
            "FT-": "4",
            "PTS": 20,
            "OREB": "4",
            "REB": 10,
            "AST": 4,
            "ST": 1,
            "BLK": 1,
            "TO": 1,
            "TF": "0",
            "EJ": "0",
            "3D": "0",
            "2D": "1"
        },
        {
            "Date": "Feb 15",
            "Team": "CLE",
            "Opp": "@GS",
            "Score": "L 98-129",
            "FPts": 63,
            "FG-": "7.0",
            "3PTM": 0,
            "FT-": "1",
            "PTS": 13,
            "OREB": "5",
            "REB": 14,
            "AST": 1,
            "ST": 1,
            "BLK": 2,
            "TO": 1,
            "TF": "0",
            "EJ": "0",
            "3D": "0",
            "2D": "1"
        },
        {
            "Date": "Feb 14",
            "Team": "CLE",
            "Opp": "@LAC",
            "Score": "L 111-128",
            "FPts": 48,
            "FG-": "4.0",
            "3PTM": 0,
            "FT-": "0",
            "PTS": 15,
            "OREB": "1",
            "REB": 10,
            "AST": 3,
            "ST": 0,
            "BLK": 0,
            "TO": 4,
            "TF": "0",
            "EJ": "0",
            "3D": "0",
            "2D": "1"
        },
        {
            "Date": "Feb 12",
            "Team": "CLE",
            "Opp": "@POR",
            "Score": "L 110-129",
            "FPts": 58,
            "FG-": "5.0",
            "3PTM": 0,
            "FT-": "7",
            "PTS": 22,
            "OREB": "5",
            "REB": 6,
            "AST": 2,
            "ST": 1,
            "BLK": 2,
            "TO": 3,
            "TF": "0",
            "EJ": "0",
            "3D": "0",
            "2D": "0"
        },
        {
            "Date": "Feb 10",
            "Team": "CLE",
            "Opp": "@DEN",
            "Score": "L 95-133",
            "FPts": 61,
            "FG-": "4.0",
            "3PTM": 0,
            "FT-": "1",
            "PTS": 18,
            "OREB": "4",
            "REB": 10,
            "AST": 2,
            "ST": 0,
            "BLK": 1,
            "TO": 2,
            "TF": "0",
            "EJ": "0",
            "3D": "0",
            "2D": "1"
        },
        {
            "Date": "Feb 8",
            "Team": "CLE",
            "Opp": "@PHO",
            "Score": "L 113-119",
            "FPts": 42,
            "FG-": "2.0",
            "3PTM": 0,
            "FT-": "1",
            "PTS": 14,
            "OREB": "2",
            "REB": 5,
            "AST": 1,
            "ST": 0,
            "BLK": 1,
            "TO": 0,
            "TF": "0",
            "EJ": "0",
            "3D": "0",
            "2D": "0"
        },
        {
            "Date": "Feb 6",
            "Team": "CLE",
            "Opp": "MIL",
            "Score": "L 99-124",
            "FPts": 18,
            "FG-": "3.0",
            "3PTM": 0,
            "FT-": "0",
            "PTS": 2,
            "OREB": "2",
            "REB": 7,
            "AST": 0,
            "ST": 0,
            "BLK": 1,
            "TO": 0,
            "TF": "0",
            "EJ": "0",
            "3D": "0",
            "2D": "0"
        },
        {
            "Date": "Feb 5",
            "Team": "CLE",
            "Opp": "MIL",
            "Score": "L 105-123",
            "FPts": 51,
            "FG-": "0.0",
            "3PTM": 1,
            "FT-": "0",
            "PTS": 13,
            "OREB": "1",
            "REB": 4,
            "AST": 3,
            "ST": 0,
            "BLK": 2,
            "TO": 2,
            "TF": "0",
            "EJ": "0",
            "3D": "0",
            "2D": "0"
        },
        {
            "Date": "Feb 3",
            "Team": "CLE",
            "Opp": "LAC",
            "Score": "L 99-121",
            "FPts": 54,
            "FG-": "5.0",
            "3PTM": 0,
            "FT-": "0",
            "PTS": 7,
            "OREB": "3",
            "REB": 9,
            "AST": 5,
            "ST": 1,
            "BLK": 2,
            "TO": 0,
            "TF": "0",
            "EJ": "0",
            "3D": "0",
            "2D": "0"
        },
        {
            "Date": "Feb 1",
            "Team": "CLE",
            "Opp": "MIN",
            "Score": "W 100-98",
            "FPts": 102,
            "FG-": "2.0",
            "3PTM": 0,
            "FT-": "5",
            "PTS": 23,
            "OREB": "4",
            "REB": 18,
            "AST": 1,
            "ST": 0,
            "BLK": 5,
            "TO": 1,
            "TF": "0",
            "EJ": "0",
            "3D": "0",
            "2D": "1"
        },
        {
            "Date": "Jan 31",
            "Team": "CLE",
            "Opp": "@MIN",
            "Score": "L 104-109",
            "FPts": 31,
            "FG-": "1.0",
            "3PTM": 0,
            "FT-": "0",
            "PTS": 10,
            "OREB": "1",
            "REB": 5,
            "AST": 0,
            "ST": 0,
            "BLK": 1,
            "TO": 1,
            "TF": "0",
            "EJ": "0",
            "3D": "0",
            "2D": "0"
        },
        {
            "Date": "Jan 29",
            "Team": "CLE",
            "Opp": "@NY",
            "Score": "L 81-102",
            "FPts": 63,
            "FG-": "3.0",
            "3PTM": 0,
            "FT-": "1",
            "PTS": 15,
            "OREB": "5",
            "REB": 9,
            "AST": 3,
            "ST": 1,
            "BLK": 1,
            "TO": 1,
            "TF": "0",
            "EJ": "0",
            "3D": "0",
            "2D": "0"
        },
        {
            "Date": "Jan 27",
            "Team": "CLE",
            "Opp": "DET",
            "Score": "W 122-107",
            "FPts": 30,
            "FG-": "2.0",
            "3PTM": 0,
            "FT-": "0",
            "PTS": 10,
            "OREB": "0",
            "REB": 1,
            "AST": 0,
            "ST": 1,
            "BLK": 2,
            "TO": 1,
            "TF": "0",
            "EJ": "0",
            "3D": "0",
            "2D": "0"
        },
        {
            "Date": "Jan 25",
            "Team": "CLE",
            "Opp": "LAL",
            "Score": "L 108-115",
            "FPts": 27,
            "FG-": "1.0",
            "3PTM": 0,
            "FT-": "0",
            "PTS": 6,
            "OREB": "3",
            "REB": 5,
            "AST": 0,
            "ST": 0,
            "BLK": 2,
            "TO": 2,
            "TF": "0",
            "EJ": "0",
            "3D": "0",
            "2D": "0"
        },
        {
            "Date": "Jan 24",
            "Team": "CLE",
            "Opp": "@BOS",
            "Score": "L 103-141",
            "FPts": 47,
            "FG-": "2.0",
            "3PTM": 0,
            "FT-": "0",
            "PTS": 12,
            "OREB": "3",
            "REB": 7,
            "AST": 2,
            "ST": 0,
            "BLK": 1,
            "TO": 0,
            "TF": "0",
            "EJ": "0",
            "3D": "0",
            "2D": "0"
        },
        {
            "Date": "Jan 22",
            "Team": "CLE",
            "Opp": "BKN",
            "Score": "W 125-113",
            "FPts": 43,
            "FG-": "2.0",
            "3PTM": 0,
            "FT-": "1",
            "PTS": 19,
            "OREB": "2",
            "REB": 6,
            "AST": 0,
            "ST": 0,
            "BLK": 0,
            "TO": 2,
            "TF": "0",
            "EJ": "0",
            "3D": "0",
            "2D": "0"
        },
        {
            "Date": "Jan 20",
            "Team": "CLE",
            "Opp": "BKN",
            "Score": "W 147-135",
            "FPts": 71,
            "FG-": "4.0",
            "3PTM": 0,
            "FT-": "0",
            "PTS": 12,
            "OREB": "3",
            "REB": 11,
            "AST": 2,
            "ST": 1,
            "BLK": 4,
            "TO": 1,
            "TF": "0",
            "EJ": "0",
            "3D": "0",
            "2D": "1"
        },
        {
            "Date": "Jan 12",
            "Team": "BKN",
            "Opp": "DEN",
            "Score": "W 122-116",
            "FPts": 34,
            "FG-": "3.0",
            "3PTM": 0,
            "FT-": "1",
            "PTS": 6,
            "OREB": "0",
            "REB": 5,
            "AST": 3,
            "ST": 1,
            "BLK": 2,
            "TO": 2,
            "TF": "0",
            "EJ": "0",
            "3D": "0",
            "2D": "0"
        },
        {
            "Date": "Jan 10",
            "Team": "BKN",
            "Opp": "OKC",
            "Score": "L 116-129",
            "FPts": 54,
            "FG-": "1.0",
            "3PTM": 0,
            "FT-": "0",
            "PTS": 15,
            "OREB": "1",
            "REB": 10,
            "AST": 1,
            "ST": 0,
            "BLK": 1,
            "TO": 3,
            "TF": "0",
            "EJ": "0",
            "3D": "0",
            "2D": "1"
        },
        {
            "Date": "Jan 8",
            "Team": "BKN",
            "Opp": "@MEM",
            "Score": "L 110-115",
            "FPts": 54,
            "FG-": "4.0",
            "3PTM": 0,
            "FT-": "1",
            "PTS": 12,
            "OREB": "3",
            "REB": 6,
            "AST": 6,
            "ST": 1,
            "BLK": 1,
            "TO": 2,
            "TF": "0",
            "EJ": "0",
            "3D": "0",
            "2D": "0"
        },
        {
            "Date": "Jan 7",
            "Team": "BKN",
            "Opp": "PHI",
            "Score": "W 122-109",
            "FPts": 57,
            "FG-": "1.0",
            "3PTM": 0,
            "FT-": "1",
            "PTS": 15,
            "OREB": "3",
            "REB": 11,
            "AST": 3,
            "ST": 0,
            "BLK": 1,
            "TO": 3,
            "TF": "1",
            "EJ": "0",
            "3D": "0",
            "2D": "1"
        },
        {
            "Date": "Jan 5",
            "Team": "BKN",
            "Opp": "UTA",
            "Score": "W 130-96",
            "FPts": 106,
            "FG-": "1.0",
            "3PTM": 0,
            "FT-": "4",
            "PTS": 19,
            "OREB": "5",
            "REB": 18,
            "AST": 1,
            "ST": 3,
            "BLK": 2,
            "TO": 0,
            "TF": "0",
            "EJ": "0",
            "3D": "0",
            "2D": "1"
        },
        {
            "Date": "Jan 3",
            "Team": "BKN",
            "Opp": "WAS",
            "Score": "L 122-123",
            "FPts": 65,
            "FG-": "3.0",
            "3PTM": 0,
            "FT-": "1",
            "PTS": 14,
            "OREB": "2",
            "REB": 11,
            "AST": 0,
            "ST": 1,
            "BLK": 4,
            "TO": 3,
            "TF": "0",
            "EJ": "0",
            "3D": "0",
            "2D": "1"
        },
        {
            "Date": "Jan 1",
            "Team": "BKN",
            "Opp": "ATL",
            "Score": "L 96-114",
            "FPts": 22,
            "FG-": "1.0",
            "3PTM": 0,
            "FT-": "0",
            "PTS": 5,
            "OREB": "2",
            "REB": 4,
            "AST": 0,
            "ST": 0,
            "BLK": 1,
            "TO": 0,
            "TF": "0",
            "EJ": "0",
            "3D": "0",
            "2D": "0"
        },
        {
            "Date": "Dec 30",
            "Team": "BKN",
            "Opp": "ATL",
            "Score": "W 145-141",
            "FPts": 60,
            "FG-": "1.0",
            "3PTM": 0,
            "FT-": "2",
            "PTS": 15,
            "OREB": "5",
            "REB": 13,
            "AST": 1,
            "ST": 0,
            "BLK": 0,
            "TO": 2,
            "TF": "0",
            "EJ": "0",
            "3D": "0",
            "2D": "1"
        },
        {
            "Date": "Dec 28",
            "Team": "BKN",
            "Opp": "MEM",
            "Score": "L 111-116",
            "FPts": 43,
            "FG-": "3.0",
            "3PTM": 0,
            "FT-": "1",
            "PTS": 8,
            "OREB": "5",
            "REB": 15,
            "AST": 1,
            "ST": 0,
            "BLK": 0,
            "TO": 2,
            "TF": "0",
            "EJ": "0",
            "3D": "0",
            "2D": "0"
        },
        {
            "Date": "Dec 27",
            "Team": "BKN",
            "Opp": "@CHA",
            "Score": "L 104-106",
            "FPts": 41,
            "FG-": "1.0",
            "3PTM": 0,
            "FT-": "2",
            "PTS": 8,
            "OREB": "4",
            "REB": 14,
            "AST": 1,
            "ST": 0,
            "BLK": 1,
            "TO": 2,
            "TF": "1",
            "EJ": "0",
            "3D": "0",
            "2D": "0"
        },
        {
            "Date": "Dec 25",
            "Team": "BKN",
            "Opp": "@BOS",
            "Score": "W 123-95",
            "FPts": 59,
            "FG-": "1.0",
            "3PTM": 0,
            "FT-": "1",
            "PTS": 9,
            "OREB": "5",
            "REB": 11,
            "AST": 1,
            "ST": 0,
            "BLK": 4,
            "TO": 1,
            "TF": "0",
            "EJ": "0",
            "3D": "0",
            "2D": "0"
        },
        {
            "Date": "Dec 22",
            "Team": "BKN",
            "Opp": "GS",
            "Score": "W 125-99",
            "FPts": 46,
            "FG-": "1.0",
            "3PTM": 0,
            "FT-": "1",
            "PTS": 8,
            "OREB": "3",
            "REB": 7,
            "AST": 2,
            "ST": 1,
            "BLK": 2,
            "TO": 2,
            "TF": "0",
            "EJ": "0",
            "3D": "0",
            "2D": "0"
        }
    ],
    "status": "success"
}