{
    "player_name": "Vince Williams",
    "player_code": "0622a",
    "league_id": "ifa1anexmdgtlk9s",
    "season": "2023-24",
    "timestamp": 1764614525.852379,
    "data": [
        {
            "Date": "Mar 8",
            "Team": "MEM",
            "Opp": "ATL",
            "Score": "L 92-99",
            "FPts": 48,
            "MIN": 36.81666666666667,
            "FGM": 4,
            "FGA": 8,
            "FG%": 0.5,
            "3PTM": 3,
            "3PTA": 5,
            "3PT%": 0.6,
            "FTM": 3,
            "FTA": 4,
            "FT%": 0.75,
            "REB": 5,
            "AST": 6,
            "ST": 0,
            "BLK": 1,
            "TO": 6,
            "PF": 4,
            "PTS": 14
        },
        {
            "Date": "Mar 6",
            "Team": "MEM",
            "Opp": "@PHI",
            "Score": "W 115-109",
            "FPts": 86,
            "MIN": 36.7,
            "FGM": 6,
            "FGA": 9,
            "FG%": 0.667,
            "3PTM": 2,
            "3PTA": 3,
            "3PT%": 0.667,
            "FTM": 3,
            "FTA": 3,
            "FT%": 1.0,
            "REB": 7,
            "AST": 9,
            "ST": 2,
            "BLK": 1,
            "TO": 3,
            "PF": 2,
            "PTS": 17
        },
        {
            "Date": "Mar 4",
            "Team": "MEM",
            "Opp": "@BKN",
            "Score": "W 106-102",
            "FPts": 48,
            "MIN": 33.95,
            "FGM": 4,
            "FGA": 11,
            "FG%": 0.364,
            "3PTM": 1,
            "3PTA": 4,
            "3PT%": 0.25,
            "FTM": 2,
            "FTA": 2,
            "FT%": 1.0,
            "REB": 5,
            "AST": 6,
            "ST": 2,
            "BLK": 0,
            "TO": 2,
            "PF": 3,
            "PTS": 11
        },
        {
            "Date": "Mar 2",
            "Team": "MEM",
            "Opp": "POR",
            "Score": "L 100-107",
            "FPts": 72,
            "MIN": 38.083333333333336,
            "FGM": 7,
            "FGA": 14,
            "FG%": 0.5,
            "3PTM": 4,
            "3PTA": 7,
            "3PT%": 0.571,
            "FTM": 3,
            "FTA": 4,
            "FT%": 0.75,
            "REB": 8,
            "AST": 2,
            "ST": 2,
            "BLK": 3,
            "TO": 4,
            "PF": 4,
            "PTS": 21
        },
        {
            "Date": "Mar 1",
            "Team": "MEM",
            "Opp": "POR",
            "Score": "L 92-122",
            "FPts": 24,
            "MIN": 28.666666666666668,
            "FGM": 3,
            "FGA": 7,
            "FG%": 0.429,
            "3PTM": 0,
            "3PTA": 0,
            "3PT%": NaN,
            "FTM": 2,
            "FTA": 5,
            "FT%": 0.4,
            "REB": 2,
            "AST": 5,
            "ST": 0,
            "BLK": 2,
            "TO": 4,
            "PF": 2,
            "PTS": 8
        },
        {
            "Date": "Feb 28",
            "Team": "MEM",
            "Opp": "@MIN",
            "Score": "L 101-110",
            "FPts": 39,
            "MIN": 30.933333333333334,
            "FGM": 4,
            "FGA": 15,
            "FG%": 0.267,
            "3PTM": 1,
            "3PTA": 5,
            "3PT%": 0.2,
            "FTM": 2,
            "FTA": 2,
            "FT%": 1.0,
            "REB": 6,
            "AST": 6,
            "ST": 1,
            "BLK": 1,
            "TO": 3,
            "PF": 3,
            "PTS": 11
        },
        {
            "Date": "Feb 26",
            "Team": "MEM",
            "Opp": "BKN",
            "Score": "L 86-111",
            "FPts": 21,
            "MIN": 24.766666666666666,
            "FGM": 2,
            "FGA": 5,
            "FG%": 0.4,
            "3PTM": 1,
            "3PTA": 2,
            "3PT%": 0.5,
            "FTM": 1,
            "FTA": 2,
            "FT%": 0.5,
            "REB": 3,
            "AST": 5,
            "ST": 0,
            "BLK": 0,
            "TO": 4,
            "PF": 3,
            "PTS": 6
        },
        {
            "Date": "Feb 23",
            "Team": "MEM",
            "Opp": "LAC",
            "Score": "L 95-101",
            "FPts": 46,
            "MIN": 35.63333333333333,
            "FGM": 4,
            "FGA": 6,
            "FG%": 0.667,
            "3PTM": 1,
            "3PTA": 2,
            "3PT%": 0.5,
            "FTM": 0,
            "FTA": 0,
            "FT%": NaN,
            "REB": 6,
            "AST": 8,
            "ST": 0,
            "BLK": 0,
            "TO": 4,
            "PF": 3,
            "PTS": 9
        },
        {
            "Date": "Feb 15",
            "Team": "MEM",
            "Opp": "MIL",
            "Score": "W 113-110",
            "FPts": 86,
            "MIN": 34.1,
            "FGM": 7,
            "FGA": 11,
            "FG%": 0.636,
            "3PTM": 0,
            "3PTA": 2,
            "3PT%": 0.0,
            "FTM": 4,
            "FTA": 4,
            "FT%": 1.0,
            "REB": 12,
            "AST": 7,
            "ST": 2,
            "BLK": 0,
            "TO": 2,
            "PF": 5,
            "PTS": 18
        },
        {
            "Date": "Feb 14",
            "Team": "MEM",
            "Opp": "HOU",
            "Score": "W 121-113",
            "FPts": 68,
            "MIN": 34.53333333333333,
            "FGM": 1,
            "FGA": 6,
            "FG%": 0.167,
            "3PTM": 0,
            "3PTA": 4,
            "3PT%": 0.0,
            "FTM": 10,
            "FTA": 12,
            "FT%": 0.833,
            "REB": 8,
            "AST": 7,
            "ST": 3,
            "BLK": 1,
            "TO": 2,
            "PF": 1,
            "PTS": 12
        },
        {
            "Date": "Feb 12",
            "Team": "MEM",
            "Opp": "NO",
            "Score": "L 87-96",
            "FPts": 50,
            "MIN": 37.03333333333333,
            "FGM": 4,
            "FGA": 8,
            "FG%": 0.5,
            "3PTM": 1,
            "3PTA": 5,
            "3PT%": 0.2,
            "FTM": 3,
            "FTA": 3,
            "FT%": 1.0,
            "REB": 3,
            "AST": 9,
            "ST": 1,
            "BLK": 0,
            "TO": 4,
            "PF": 2,
            "PTS": 12
        },
        {
            "Date": "Feb 10",
            "Team": "MEM",
            "Opp": "@CHA",
            "Score": "L 106-115",
            "FPts": 54,
            "MIN": 36.78333333333333,
            "FGM": 6,
            "FGA": 13,
            "FG%": 0.462,
            "3PTM": 2,
            "3PTA": 6,
            "3PT%": 0.333,
            "FTM": 0,
            "FTA": 0,
            "FT%": NaN,
            "REB": 2,
            "AST": 8,
            "ST": 2,
            "BLK": 0,
            "TO": 3,
            "PF": 3,
            "PTS": 14
        },
        {
            "Date": "Feb 8",
            "Team": "MEM",
            "Opp": "CHI",
            "Score": "L 110-118",
            "FPts": 88,
            "MIN": 37.31666666666667,
            "FGM": 5,
            "FGA": 10,
            "FG%": 0.5,
            "3PTM": 2,
            "3PTA": 5,
            "3PT%": 0.4,
            "FTM": 1,
            "FTA": 1,
            "FT%": 1.0,
            "REB": 11,
            "AST": 8,
            "ST": 3,
            "BLK": 0,
            "TO": 1,
            "PF": 2,
            "PTS": 13
        },
        {
            "Date": "Feb 6",
            "Team": "MEM",
            "Opp": "@NY",
            "Score": "L 113-123",
            "FPts": 39,
            "MIN": 34.833333333333336,
            "FGM": 6,
            "FGA": 17,
            "FG%": 0.353,
            "3PTM": 3,
            "3PTA": 5,
            "3PT%": 0.6,
            "FTM": 4,
            "FTA": 4,
            "FT%": 1.0,
            "REB": 3,
            "AST": 5,
            "ST": 1,
            "BLK": 0,
            "TO": 4,
            "PF": 4,
            "PTS": 19
        },
        {
            "Date": "Feb 2",
            "Team": "MEM",
            "Opp": "GS",
            "Score": "L 101-121",
            "FPts": 39,
            "MIN": 31.483333333333334,
            "FGM": 6,
            "FGA": 12,
            "FG%": 0.5,
            "3PTM": 1,
            "3PTA": 5,
            "3PT%": 0.2,
            "FTM": 2,
            "FTA": 5,
            "FT%": 0.4,
            "REB": 6,
            "AST": 4,
            "ST": 0,
            "BLK": 1,
            "TO": 4,
            "PF": 5,
            "PTS": 15
        },
        {
            "Date": "Feb 1",
            "Team": "MEM",
            "Opp": "CLE",
            "Score": "L 101-108",
            "FPts": 53,
            "MIN": 30.916666666666668,
            "FGM": 5,
            "FGA": 10,
            "FG%": 0.5,
            "3PTM": 1,
            "3PTA": 5,
            "3PT%": 0.2,
            "FTM": 6,
            "FTA": 6,
            "FT%": 1.0,
            "REB": 6,
            "AST": 2,
            "ST": 1,
            "BLK": 1,
            "TO": 2,
            "PF": 2,
            "PTS": 17
        },
        {
            "Date": "Jan 28",
            "Team": "MEM",
            "Opp": "@IND",
            "Score": "L 110-116",
            "FPts": 59,
            "MIN": 36.05,
            "FGM": 8,
            "FGA": 12,
            "FG%": 0.667,
            "3PTM": 2,
            "3PTA": 3,
            "3PT%": 0.667,
            "FTM": 2,
            "FTA": 4,
            "FT%": 0.5,
            "REB": 8,
            "AST": 1,
            "ST": 0,
            "BLK": 0,
            "TO": 0,
            "PF": 3,
            "PTS": 20
        },
        {
            "Date": "Jan 26",
            "Team": "MEM",
            "Opp": "ORL",
            "Score": "W 107-106",
            "FPts": 39,
            "MIN": 35.8,
            "FGM": 3,
            "FGA": 9,
            "FG%": 0.333,
            "3PTM": 3,
            "3PTA": 8,
            "3PT%": 0.375,
            "FTM": 2,
            "FTA": 4,
            "FT%": 0.5,
            "REB": 5,
            "AST": 4,
            "ST": 0,
            "BLK": 2,
            "TO": 1,
            "PF": 4,
            "PTS": 11
        },
        {
            "Date": "Jan 24",
            "Team": "MEM",
            "Opp": "@MIA",
            "Score": "W 105-96",
            "FPts": 87,
            "MIN": 32.68333333333333,
            "FGM": 8,
            "FGA": 10,
            "FG%": 0.8,
            "3PTM": 5,
            "3PTA": 6,
            "3PT%": 0.833,
            "FTM": 4,
            "FTA": 4,
            "FT%": 1.0,
            "REB": 5,
            "AST": 4,
            "ST": 1,
            "BLK": 0,
            "TO": 1,
            "PF": 3,
            "PTS": 25
        },
        {
            "Date": "Jan 22",
            "Team": "MEM",
            "Opp": "@TOR",
            "Score": "W 108-100",
            "FPts": 75,
            "MIN": 35.016666666666666,
            "FGM": 7,
            "FGA": 11,
            "FG%": 0.636,
            "3PTM": 2,
            "3PTA": 4,
            "3PT%": 0.5,
            "FTM": 2,
            "FTA": 3,
            "FT%": 0.667,
            "REB": 10,
            "AST": 1,
            "ST": 2,
            "BLK": 1,
            "TO": 2,
            "PF": 2,
            "PTS": 18
        },
        {
            "Date": "Jan 20",
            "Team": "MEM",
            "Opp": "@CHI",
            "Score": "L 96-125",
            "FPts": 46,
            "MIN": 29.883333333333333,
            "FGM": 5,
            "FGA": 9,
            "FG%": 0.556,
            "3PTM": 3,
            "3PTA": 6,
            "3PT%": 0.5,
            "FTM": 1,
            "FTA": 2,
            "FT%": 0.5,
            "REB": 5,
            "AST": 2,
            "ST": 1,
            "BLK": 0,
            "TO": 2,
            "PF": 2,
            "PTS": 14
        },
        {
            "Date": "Jan 18",
            "Team": "MEM",
            "Opp": "@MIN",
            "Score": "L 103-118",
            "FPts": 65,
            "MIN": 34.61666666666667,
            "FGM": 3,
            "FGA": 8,
            "FG%": 0.375,
            "3PTM": 2,
            "3PTA": 5,
            "3PT%": 0.4,
            "FTM": 2,
            "FTA": 2,
            "FT%": 1.0,
            "REB": 7,
            "AST": 5,
            "ST": 3,
            "BLK": 1,
            "TO": 2,
            "PF": 3,
            "PTS": 10
        },
        {
            "Date": "Jan 15",
            "Team": "MEM",
            "Opp": "GS",
            "Score": "W 116-107",
            "FPts": 85,
            "MIN": 37.86666666666667,
            "FGM": 6,
            "FGA": 11,
            "FG%": 0.545,
            "3PTM": 3,
            "3PTA": 6,
            "3PT%": 0.5,
            "FTM": 9,
            "FTA": 10,
            "FT%": 0.9,
            "REB": 7,
            "AST": 4,
            "ST": 2,
            "BLK": 1,
            "TO": 3,
            "PF": 2,
            "PTS": 24
        },
        {
            "Date": "Jan 13",
            "Team": "MEM",
            "Opp": "NY",
            "Score": "L 94-106",
            "FPts": 70,
            "MIN": 35.7,
            "FGM": 5,
            "FGA": 13,
            "FG%": 0.385,
            "3PTM": 1,
            "3PTA": 7,
            "3PT%": 0.143,
            "FTM": 6,
            "FTA": 8,
            "FT%": 0.75,
            "REB": 8,
            "AST": 8,
            "ST": 2,
            "BLK": 1,
            "TO": 4,
            "PF": 1,
            "PTS": 17
        },
        {
            "Date": "Jan 12",
            "Team": "MEM",
            "Opp": "LAC",
            "Score": "L 119-128",
            "FPts": 25,
            "MIN": 26.533333333333335,
            "FGM": 2,
            "FGA": 6,
            "FG%": 0.333,
            "3PTM": 2,
            "3PTA": 5,
            "3PT%": 0.4,
            "FTM": 0,
            "FTA": 0,
            "FT%": NaN,
            "REB": 3,
            "AST": 1,
            "ST": 1,
            "BLK": 0,
            "TO": 1,
            "PF": 2,
            "PTS": 6
        },
        {
            "Date": "Jan 9",
            "Team": "MEM",
            "Opp": "@DAL",
            "Score": "W 120-103",
            "FPts": 50,
            "MIN": 29.616666666666667,
            "FGM": 2,
            "FGA": 8,
            "FG%": 0.25,
            "3PTM": 2,
            "3PTA": 5,
            "3PT%": 0.4,
            "FTM": 0,
            "FTA": 0,
            "FT%": NaN,
            "REB": 6,
            "AST": 6,
            "ST": 3,
            "BLK": 0,
            "TO": 3,
            "PF": 5,
            "PTS": 6
        },
        {
            "Date": "Jan 7",
            "Team": "MEM",
            "Opp": "@PHO",
            "Score": "W 121-115",
            "FPts": 70,
            "MIN": 36.96666666666667,
            "FGM": 6,
            "FGA": 11,
            "FG%": 0.545,
            "3PTM": 3,
            "3PTA": 4,
            "3PT%": 0.75,
            "FTM": 4,
            "FTA": 4,
            "FT%": 1.0,
            "REB": 9,
            "AST": 1,
            "ST": 0,
            "BLK": 2,
            "TO": 0,
            "PF": 2,
            "PTS": 19
        },
        {
            "Date": "Jan 2",
            "Team": "MEM",
            "Opp": "SA",
            "Score": "W 106-98",
            "FPts": 29,
            "MIN": 21.966666666666665,
            "FGM": 3,
            "FGA": 6,
            "FG%": 0.5,
            "3PTM": 2,
            "3PTA": 5,
            "3PT%": 0.4,
            "FTM": 0,
            "FTA": 0,
            "FT%": NaN,
            "REB": 5,
            "AST": 2,
            "ST": 0,
            "BLK": 0,
            "TO": 2,
            "PF": 5,
            "PTS": 8
        },
        {
            "Date": "Dec 31",
            "Team": "MEM",
            "Opp": "SAC",
            "Score": "L 92-123",
            "FPts": 7,
            "MIN": 17.683333333333334,
            "FGM": 0,
            "FGA": 4,
            "FG%": 0.0,
            "3PTM": 0,
            "3PTA": 4,
            "3PT%": 0.0,
            "FTM": 0,
            "FTA": 0,
            "FT%": NaN,
            "REB": 6,
            "AST": 1,
            "ST": 0,
            "BLK": 0,
            "TO": 0,
            "PF": 1,
            "PTS": 0
        },
        {
            "Date": "Dec 29",
            "Team": "MEM",
            "Opp": "@LAC",
            "Score": "L 106-117",
            "FPts": 21,
            "MIN": 22.216666666666665,
            "FGM": 1,
            "FGA": 6,
            "FG%": 0.167,
            "3PTM": 1,
            "3PTA": 4,
            "3PT%": 0.25,
            "FTM": 2,
            "FTA": 3,
            "FT%": 0.667,
            "REB": 1,
            "AST": 5,
            "ST": 0,
            "BLK": 1,
            "TO": 1,
            "PF": 3,
            "PTS": 5
        },
        {
            "Date": "Dec 28",
            "Team": "MEM",
            "Opp": "@DEN",
            "Score": "L 105-142",
            "FPts": 33,
            "MIN": 29.783333333333335,
            "FGM": 1,
            "FGA": 7,
            "FG%": 0.143,
            "3PTM": 1,
            "3PTA": 4,
            "3PT%": 0.25,
            "FTM": 2,
            "FTA": 2,
            "FT%": 1.0,
            "REB": 11,
            "AST": 2,
            "ST": 0,
            "BLK": 0,
            "TO": 0,
            "PF": 3,
            "PTS": 5
        },
        {
            "Date": "Dec 26",
            "Team": "MEM",
            "Opp": "@NO",
            "Score": "W 116-115",
            "FPts": 49,
            "MIN": 27.0,
            "FGM": 1,
            "FGA": 4,
            "FG%": 0.25,
            "3PTM": 1,
            "3PTA": 4,
            "3PT%": 0.25,
            "FTM": 3,
            "FTA": 4,
            "FT%": 0.75,
            "REB": 8,
            "AST": 3,
            "ST": 1,
            "BLK": 3,
            "TO": 2,
            "PF": 0,
            "PTS": 6
        },
        {
            "Date": "Dec 23",
            "Team": "MEM",
            "Opp": "@ATL",
            "Score": "W 125-119",
            "FPts": 42,
            "MIN": 35.11666666666667,
            "FGM": 2,
            "FGA": 6,
            "FG%": 0.333,
            "3PTM": 1,
            "3PTA": 5,
            "3PT%": 0.2,
            "FTM": 0,
            "FTA": 0,
            "FT%": NaN,
            "REB": 11,
            "AST": 1,
            "ST": 2,
            "BLK": 0,
            "TO": 1,
            "PF": 4,
            "PTS": 5
        },
        {
            "Date": "Dec 21",
            "Team": "MEM",
            "Opp": "IND",
            "Score": "W 116-103",
            "FPts": 32,
            "MIN": 34.65,
            "FGM": 1,
            "FGA": 5,
            "FG%": 0.2,
            "3PTM": 0,
            "3PTA": 3,
            "3PT%": 0.0,
            "FTM": 0,
            "FTA": 0,
            "FT%": NaN,
            "REB": 4,
            "AST": 3,
            "ST": 3,
            "BLK": 1,
            "TO": 2,
            "PF": 2,
            "PTS": 2
        },
        {
            "Date": "Dec 19",
            "Team": "MEM",
            "Opp": "@NO",
            "Score": "W 115-113",
            "FPts": 47,
            "MIN": 34.666666666666664,
            "FGM": 3,
            "FGA": 6,
            "FG%": 0.5,
            "3PTM": 3,
            "3PTA": 5,
            "3PT%": 0.6,
            "FTM": 0,
            "FTA": 0,
            "FT%": NaN,
            "REB": 7,
            "AST": 3,
            "ST": 0,
            "BLK": 1,
            "TO": 1,
            "PF": 1,
            "PTS": 9
        },
        {
            "Date": "Dec 18",
            "Team": "MEM",
            "Opp": "@OKC",
            "Score": "L 97-116",
            "FPts": 16,
            "MIN": 23.133333333333333,
            "FGM": 2,
            "FGA": 7,
            "FG%": 0.286,
            "3PTM": 1,
            "3PTA": 5,
            "3PT%": 0.2,
            "FTM": 0,
            "FTA": 0,
            "FT%": NaN,
            "REB": 5,
            "AST": 1,
            "ST": 0,
            "BLK": 0,
            "TO": 1,
            "PF": 3,
            "PTS": 5
        },
        {
            "Date": "Dec 15",
            "Team": "MEM",
            "Opp": "HOU",
            "Score": "L 96-103",
            "FPts": 57,
            "MIN": 30.3,
            "FGM": 4,
            "FGA": 8,
            "FG%": 0.5,
            "3PTM": 3,
            "3PTA": 6,
            "3PT%": 0.5,
            "FTM": 0,
            "FTA": 0,
            "FT%": NaN,
            "REB": 8,
            "AST": 3,
            "ST": 1,
            "BLK": 2,
            "TO": 3,
            "PF": 2,
            "PTS": 11
        },
        {
            "Date": "Dec 13",
            "Team": "MEM",
            "Opp": "@HOU",
            "Score": "L 104-117",
            "FPts": 42,
            "MIN": 27.783333333333335,
            "FGM": 2,
            "FGA": 5,
            "FG%": 0.4,
            "3PTM": 2,
            "3PTA": 4,
            "3PT%": 0.5,
            "FTM": 4,
            "FTA": 6,
            "FT%": 0.667,
            "REB": 7,
            "AST": 1,
            "ST": 1,
            "BLK": 0,
            "TO": 0,
            "PF": 6,
            "PTS": 10
        },
        {
            "Date": "Dec 11",
            "Team": "MEM",
            "Opp": "DAL",
            "Score": "L 113-120",
            "FPts": 46,
            "MIN": 25.733333333333334,
            "FGM": 3,
            "FGA": 4,
            "FG%": 0.75,
            "3PTM": 2,
            "3PTA": 3,
            "3PT%": 0.667,
            "FTM": 2,
            "FTA": 2,
            "FT%": 1.0,
            "REB": 9,
            "AST": 1,
            "ST": 0,
            "BLK": 0,
            "TO": 1,
            "PF": 3,
            "PTS": 10
        },
        {
            "Date": "Dec 8",
            "Team": "MEM",
            "Opp": "MIN",
            "Score": "L 103-127",
            "FPts": 8,
            "MIN": 17.016666666666666,
            "FGM": 1,
            "FGA": 5,
            "FG%": 0.2,
            "3PTM": 1,
            "3PTA": 4,
            "3PT%": 0.25,
            "FTM": 1,
            "FTA": 2,
            "FT%": 0.5,
            "REB": 2,
            "AST": 1,
            "ST": 0,
            "BLK": 0,
            "TO": 1,
            "PF": 1,
            "PTS": 4
        },
        {
            "Date": "Dec 6",
            "Team": "MEM",
            "Opp": "@DET",
            "Score": "W 116-102",
            "FPts": 24,
            "MIN": 24.766666666666666,
            "FGM": 1,
            "FGA": 2,
            "FG%": 0.5,
            "3PTM": 1,
            "3PTA": 2,
            "3PT%": 0.5,
            "FTM": 0,
            "FTA": 0,
            "FT%": NaN,
            "REB": 4,
            "AST": 1,
            "ST": 1,
            "BLK": 0,
            "TO": 0,
            "PF": 0,
            "PTS": 3
        },
        {
            "Date": "Dec 2",
            "Team": "MEM",
            "Opp": "@PHO",
            "Score": "L 109-116",
            "FPts": 37,
            "MIN": 29.75,
            "FGM": 3,
            "FGA": 5,
            "FG%": 0.6,
            "3PTM": 1,
            "3PTA": 3,
            "3PT%": 0.333,
            "FTM": 5,
            "FTA": 5,
            "FT%": 1.0,
            "REB": 5,
            "AST": 2,
            "ST": 0,
            "BLK": 0,
            "TO": 1,
            "PF": 6,
            "PTS": 12
        },
        {
            "Date": "Dec 1",
            "Team": "MEM",
            "Opp": "@DAL",
            "Score": "W 108-94",
            "FPts": 68,
            "MIN": 26.066666666666666,
            "FGM": 6,
            "FGA": 9,
            "FG%": 0.667,
            "3PTM": 3,
            "3PTA": 6,
            "3PT%": 0.5,
            "FTM": 0,
            "FTA": 0,
            "FT%": NaN,
            "REB": 9,
            "AST": 3,
            "ST": 0,
            "BLK": 2,
            "TO": 1,
            "PF": 4,
            "PTS": 15
        },
        {
            "Date": "Nov 29",
            "Team": "MEM",
            "Opp": "UTA",
            "Score": "W 105-91",
            "FPts": 31,
            "MIN": 19.516666666666666,
            "FGM": 1,
            "FGA": 3,
            "FG%": 0.333,
            "3PTM": 1,
            "3PTA": 3,
            "3PT%": 0.333,
            "FTM": 0,
            "FTA": 0,
            "FT%": NaN,
            "REB": 8,
            "AST": 2,
            "ST": 1,
            "BLK": 0,
            "TO": 2,
            "PF": 3,
            "PTS": 3
        },
        {
            "Date": "Nov 26",
            "Team": "MEM",
            "Opp": "MIN",
            "Score": "L 97-119",
            "FPts": 12,
            "MIN": 9.85,
            "FGM": 0,
            "FGA": 2,
            "FG%": 0.0,
            "3PTM": 0,
            "3PTA": 2,
            "3PT%": 0.0,
            "FTM": 0,
            "FTA": 0,
            "FT%": NaN,
            "REB": 3,
            "AST": 1,
            "ST": 1,
            "BLK": 0,
            "TO": 0,
            "PF": 1,
            "PTS": 0
        },
        {
            "Date": "Nov 24",
            "Team": "MEM",
            "Opp": "PHO",
            "Score": "L 89-110",
            "FPts": 20,
            "MIN": 13.716666666666667,
            "FGM": 1,
            "FGA": 2,
            "FG%": 0.5,
            "3PTM": 1,
            "3PTA": 2,
            "3PT%": 0.5,
            "FTM": 0,
            "FTA": 0,
            "FT%": NaN,
            "REB": 5,
            "AST": 1,
            "ST": 0,
            "BLK": 0,
            "TO": 0,
            "PF": 4,
            "PTS": 3
        },
        {
            "Date": "Nov 22",
            "Team": "MEM",
            "Opp": "@HOU",
            "Score": "L 91-111",
            "FPts": 0,
            "MIN": 4.25,
            "FGM": 0,
            "FGA": 1,
            "FG%": 0.0,
            "3PTM": 0,
            "3PTA": 1,
            "3PT%": 0.0,
            "FTM": 0,
            "FTA": 0,
            "FT%": NaN,
            "REB": 1,
            "AST": 0,
            "ST": 0,
            "BLK": 0,
            "TO": 0,
            "PF": 0,
            "PTS": 0
        },
        {
            "Date": "Nov 19",
            "Team": "MEM",
            "Opp": "BOS",
            "Score": "L 100-102",
            "FPts": 22,
            "MIN": 16.5,
            "FGM": 2,
            "FGA": 4,
            "FG%": 0.5,
            "3PTM": 2,
            "3PTA": 3,
            "3PT%": 0.667,
            "FTM": 0,
            "FTA": 0,
            "FT%": NaN,
            "REB": 0,
            "AST": 0,
            "ST": 0,
            "BLK": 2,
            "TO": 0,
            "PF": 2,
            "PTS": 6
        },
        {
            "Date": "Nov 14",
            "Team": "MEM",
            "Opp": "@LAL",
            "Score": "L 107-134",
            "FPts": 0,
            "MIN": 5.016666666666667,
            "FGM": 0,
            "FGA": 1,
            "FG%": 0.0,
            "3PTM": 0,
            "3PTA": 1,
            "3PT%": 0.0,
            "FTM": 0,
            "FTA": 0,
            "FT%": NaN,
            "REB": 1,
            "AST": 0,
            "ST": 0,
            "BLK": 0,
            "TO": 0,
            "PF": 0,
            "PTS": 0
        },
        {
            "Date": "Nov 3",
            "Team": "MEM",
            "Opp": "@POR",
            "Score": "L 113-115",
            "FPts": 1,
            "MIN": 9.983333333333333,
            "FGM": 0,
            "FGA": 2,
            "FG%": 0.0,
            "3PTM": 0,
            "3PTA": 2,
            "3PT%": 0.0,
            "FTM": 0,
            "FTA": 0,
            "FT%": NaN,
            "REB": 2,
            "AST": 1,
            "ST": 0,
            "BLK": 0,
            "TO": 1,
            "PF": 1,
            "PTS": 0
        },
        {
            "Date": "Nov 1",
            "Team": "MEM",
            "Opp": "@UTA",
            "Score": "L 109-133",
            "FPts": 49,
            "MIN": 16.1,
            "FGM": 2,
            "FGA": 5,
            "FG%": 0.4,
            "3PTM": 1,
            "3PTA": 4,
            "3PT%": 0.25,
            "FTM": 7,
            "FTA": 8,
            "FT%": 0.875,
            "REB": 2,
            "AST": 3,
            "ST": 1,
            "BLK": 3,
            "TO": 1,
            "PF": 3,
            "PTS": 12
        },
        {
            "Date": "Oct 30",
            "Team": "MEM",
            "Opp": "DAL",
            "Score": "L 110-125",
            "FPts": 0,
            "MIN": 0.6333333333333333,
            "FGM": 0,
            "FGA": 0,
            "FG%": NaN,
            "3PTM": 0,
            "3PTA": 0,
            "3PT%": NaN,
            "FTM": 0,
            "FTA": 0,
            "FT%": NaN,
            "REB": 0,
            "AST": 0,
            "ST": 0,
            "BLK": 0,
            "TO": 0,
            "PF": 0,
            "PTS": 0
        }
    ],
    "status": "success"
}