{
    "player_name": "Zaccharie Risacher",
    "player_code": "06mjt",
    "league_id": "ifa1anexmdgtlk9s",
    "data": [
        {
            "Date": "Nov 8",
            "Team": "ATL",
            "Opp": "LAL",
            "Score": "W 122-102",
            "FPts": 57,
            "MIN": "27:06",
            "FGM": 7,
            "FGA": 14,
            "FG%": 0.5,
            "3PTM": 3,
            "3PTA": 7,
            "3PT%": 0.429,
            "FTM": 2,
            "FTA": 2,
            "FT%": 1.0,
            "REB": 1,
            "AST": 4,
            "ST": 2,
            "BLK": 0,
            "TO": 1,
            "PF": 1,
            "PTS": 19
        },
        {
            "Date": "Nov 7",
            "Team": "ATL",
            "Opp": "TOR",
            "Score": "L 97-109",
            "FPts": 43,
            "MIN": "30:26",
            "FGM": 6,
            "FGA": 16,
            "FG%": 0.375,
            "3PTM": 1,
            "3PTA": 5,
            "3PT%": 0.2,
            "FTM": 3,
            "FTA": 3,
            "FT%": 1.0,
            "REB": 5,
            "AST": 0,
            "ST": 2,
            "BLK": 1,
            "TO": 0,
            "PF": 4,
            "PTS": 16
        },
        {
            "Date": "Nov 4",
            "Team": "ATL",
            "Opp": "ORL",
            "Score": "W 127-112",
            "FPts": 55,
            "MIN": "25:30",
            "FGM": 7,
            "FGA": 14,
            "FG%": 0.5,
            "3PTM": 3,
            "3PTA": 8,
            "3PT%": 0.375,
            "FTM": 4,
            "FTA": 4,
            "FT%": 1.0,
            "REB": 4,
            "AST": 1,
            "ST": 1,
            "BLK": 0,
            "TO": 0,
            "PF": 2,
            "PTS": 21
        },
        {
            "Date": "Nov 2",
            "Team": "ATL",
            "Opp": "@CLE",
            "Score": "L 109-117",
            "FPts": 41,
            "MIN": "24:00",
            "FGM": 4,
            "FGA": 8,
            "FG%": 0.5,
            "3PTM": 0,
            "3PTA": 2,
            "3PT%": 0.0,
            "FTM": 0,
            "FTA": 0,
            "FT%": NaN,
            "REB": 2,
            "AST": 5,
            "ST": 3,
            "BLK": 0,
            "TO": 2,
            "PF": 1,
            "PTS": 8
        },
        {
            "Date": "Oct 31",
            "Team": "ATL",
            "Opp": "@IND",
            "Score": "W 128-108",
            "FPts": 35,
            "MIN": "22:35",
            "FGM": 5,
            "FGA": 12,
            "FG%": 0.417,
            "3PTM": 3,
            "3PTA": 7,
            "3PT%": 0.429,
            "FTM": 0,
            "FTA": 0,
            "FT%": NaN,
            "REB": 1,
            "AST": 1,
            "ST": 1,
            "BLK": 1,
            "TO": 1,
            "PF": 4,
            "PTS": 13
        },
        {
            "Date": "Oct 29",
            "Team": "ATL",
            "Opp": "@BKN",
            "Score": "W 117-112",
            "FPts": 24,
            "MIN": "27:48",
            "FGM": 2,
            "FGA": 7,
            "FG%": 0.286,
            "3PTM": 1,
            "3PTA": 2,
            "3PT%": 0.5,
            "FTM": 3,
            "FTA": 4,
            "FT%": 0.75,
            "REB": 3,
            "AST": 0,
            "ST": 1,
            "BLK": 1,
            "TO": 0,
            "PF": 2,
            "PTS": 8
        },
        {
            "Date": "Oct 27",
            "Team": "ATL",
            "Opp": "@CHI",
            "Score": "L 123-128",
            "FPts": -6,
            "MIN": "20:19",
            "FGM": 1,
            "FGA": 5,
            "FG%": 0.2,
            "3PTM": 0,
            "3PTA": 2,
            "3PT%": 0.0,
            "FTM": 0,
            "FTA": 0,
            "FT%": NaN,
            "REB": 0,
            "AST": 0,
            "ST": 0,
            "BLK": 0,
            "TO": 1,
            "PF": 1,
            "PTS": 2
        },
        {
            "Date": "Oct 22",
            "Team": "ATL",
            "Opp": "TOR",
            "Score": "L 118-138",
            "FPts": 36,
            "MIN": "20:36",
            "FGM": 7,
            "FGA": 13,
            "FG%": 0.538,
            "3PTM": 2,
            "3PTA": 6,
            "3PT%": 0.333,
            "FTM": 0,
            "FTA": 0,
            "FT%": NaN,
            "REB": 2,
            "AST": 0,
            "ST": 0,
            "BLK": 1,
            "TO": 0,
            "PF": 1,
            "PTS": 16
        }
    ]
}