{
    "player_name": "Josh Hart",
    "player_code": "04ewu",
    "league_id": "ifa1anexmdgtlk9s",
    "season": "2024-25",
    "data": [
        {
            "Date": "Apr 11",
            "Team": "NY",
            "Opp": "CLE",
            "Score": "L 102-108",
            "FPts": 57,
            "FG-": "3.0",
            "3PTM": 2,
            "FT-": "0",
            "PTS": 8,
            "OREB": "2",
            "REB": 11,
            "AST": 5,
            "ST": 1,
            "BLK": 0,
            "TO": 2,
            "TF": "0",
            "EJ": "0",
            "3D": "0",
            "2D": "0"
        },
        {
            "Date": "Apr 8",
            "Team": "NY",
            "Opp": "BOS",
            "Score": "L 117-119",
            "FPts": 68,
            "FG-": "9.0",
            "3PTM": 0,
            "FT-": "1",
            "PTS": 10,
            "OREB": "4",
            "REB": 11,
            "AST": 7,
            "ST": 3,
            "BLK": 0,
            "TO": 1,
            "TF": "0",
            "EJ": "0",
            "3D": "0",
            "2D": "1"
        },
        {
            "Date": "Apr 6",
            "Team": "NY",
            "Opp": "PHO",
            "Score": "W 112-98",
            "FPts": 39,
            "FG-": "4.0",
            "3PTM": 0,
            "FT-": "1",
            "PTS": 7,
            "OREB": "1",
            "REB": 10,
            "AST": 5,
            "ST": 1,
            "BLK": 0,
            "TO": 4,
            "TF": "0",
            "EJ": "0",
            "3D": "0",
            "2D": "0"
        },
        {
            "Date": "Apr 5",
            "Team": "NY",
            "Opp": "@ATL",
            "Score": "W 121-105",
            "FPts": 102,
            "FG-": "3.0",
            "3PTM": 2,
            "FT-": "1",
            "PTS": 16,
            "OREB": "0",
            "REB": 9,
            "AST": 11,
            "ST": 4,
            "BLK": 0,
            "TO": 4,
            "TF": "0",
            "EJ": "0",
            "3D": "0",
            "2D": "1"
        },
        {
            "Date": "Apr 2",
            "Team": "NY",
            "Opp": "@CLE",
            "Score": "L 105-124",
            "FPts": 55,
            "FG-": "11.0",
            "3PTM": 3,
            "FT-": "0",
            "PTS": 19,
            "OREB": "2",
            "REB": 5,
            "AST": 4,
            "ST": 2,
            "BLK": 0,
            "TO": 3,
            "TF": "0",
            "EJ": "0",
            "3D": "0",
            "2D": "0"
        },
        {
            "Date": "Apr 1",
            "Team": "NY",
            "Opp": "PHI",
            "Score": "W 105-91",
            "FPts": 48,
            "FG-": "3.0",
            "3PTM": 0,
            "FT-": "0",
            "PTS": 9,
            "OREB": "0",
            "REB": 4,
            "AST": 6,
            "ST": 2,
            "BLK": 0,
            "TO": 1,
            "TF": "0",
            "EJ": "0",
            "3D": "0",
            "2D": "0"
        },
        {
            "Date": "Mar 30",
            "Team": "NY",
            "Opp": "POR",
            "Score": "W 110-93",
            "FPts": 80,
            "FG-": "5.0",
            "3PTM": 1,
            "FT-": "1",
            "PTS": 14,
            "OREB": "1",
            "REB": 8,
            "AST": 9,
            "ST": 3,
            "BLK": 0,
            "TO": 1,
            "TF": "0",
            "EJ": "0",
            "3D": "0",
            "2D": "0"
        },
        {
            "Date": "Mar 28",
            "Team": "NY",
            "Opp": "@MIL",
            "Score": "W 116-107",
            "FPts": 92,
            "FG-": "3.0",
            "3PTM": 0,
            "FT-": "2",
            "PTS": 13,
            "OREB": "4",
            "REB": 14,
            "AST": 8,
            "ST": 2,
            "BLK": 1,
            "TO": 1,
            "TF": "0",
            "EJ": "0",
            "3D": "0",
            "2D": "1"
        },
        {
            "Date": "Mar 26",
            "Team": "NY",
            "Opp": "LAC",
            "Score": "L 113-126",
            "FPts": 29,
            "FG-": "6.0",
            "3PTM": 0,
            "FT-": "2",
            "PTS": 7,
            "OREB": "1",
            "REB": 5,
            "AST": 6,
            "ST": 0,
            "BLK": 0,
            "TO": 0,
            "TF": "0",
            "EJ": "0",
            "3D": "0",
            "2D": "0"
        },
        {
            "Date": "Mar 25",
            "Team": "NY",
            "Opp": "DAL",
            "Score": "W 128-113",
            "FPts": 102,
            "FG-": "3.0",
            "3PTM": 2,
            "FT-": "0",
            "PTS": 16,
            "OREB": "1",
            "REB": 12,
            "AST": 11,
            "ST": 2,
            "BLK": 0,
            "TO": 2,
            "TF": "0",
            "EJ": "0",
            "3D": "1",
            "2D": "1"
        },
        {
            "Date": "Mar 22",
            "Team": "NY",
            "Opp": "WAS",
            "Score": "W 122-103",
            "FPts": 40,
            "FG-": "6.0",
            "3PTM": 0,
            "FT-": "1",
            "PTS": 9,
            "OREB": "3",
            "REB": 12,
            "AST": 2,
            "ST": 1,
            "BLK": 0,
            "TO": 2,
            "TF": "0",
            "EJ": "0",
            "3D": "0",
            "2D": "0"
        },
        {
            "Date": "Mar 20",
            "Team": "NY",
            "Opp": "@CHA",
            "Score": "L 98-115",
            "FPts": 61,
            "FG-": "3.0",
            "3PTM": 3,
            "FT-": "0",
            "PTS": 13,
            "OREB": "2",
            "REB": 4,
            "AST": 6,
            "ST": 1,
            "BLK": 0,
            "TO": 1,
            "TF": "0",
            "EJ": "0",
            "3D": "0",
            "2D": "0"
        },
        {
            "Date": "Mar 19",
            "Team": "NY",
            "Opp": "@SA",
            "Score": "L 105-120",
            "FPts": 58,
            "FG-": "3.0",
            "3PTM": 0,
            "FT-": "0",
            "PTS": 2,
            "OREB": "3",
            "REB": 7,
            "AST": 7,
            "ST": 3,
            "BLK": 2,
            "TO": 2,
            "TF": "0",
            "EJ": "0",
            "3D": "0",
            "2D": "0"
        },
        {
            "Date": "Mar 17",
            "Team": "NY",
            "Opp": "MIA",
            "Score": "W 116-95",
            "FPts": 111,
            "FG-": "4.0",
            "3PTM": 2,
            "FT-": "0",
            "PTS": 12,
            "OREB": "2",
            "REB": 13,
            "AST": 11,
            "ST": 4,
            "BLK": 1,
            "TO": 2,
            "TF": "0",
            "EJ": "0",
            "3D": "1",
            "2D": "1"
        },
        {
            "Date": "Mar 15",
            "Team": "NY",
            "Opp": "@GS",
            "Score": "L 94-97",
            "FPts": 28,
            "FG-": "7.0",
            "3PTM": 0,
            "FT-": "0",
            "PTS": 0,
            "OREB": "1",
            "REB": 7,
            "AST": 7,
            "ST": 1,
            "BLK": 1,
            "TO": 2,
            "TF": "0",
            "EJ": "0",
            "3D": "0",
            "2D": "0"
        },
        {
            "Date": "Mar 12",
            "Team": "NY",
            "Opp": "@POR",
            "Score": "W 114-113",
            "FPts": 63,
            "FG-": "10.0",
            "3PTM": 2,
            "FT-": "1",
            "PTS": 11,
            "OREB": "3",
            "REB": 11,
            "AST": 9,
            "ST": 1,
            "BLK": 0,
            "TO": 3,
            "TF": "0",
            "EJ": "0",
            "3D": "0",
            "2D": "1"
        },
        {
            "Date": "Mar 10",
            "Team": "NY",
            "Opp": "@SAC",
            "Score": "W 133-104",
            "FPts": 53,
            "FG-": "5.0",
            "3PTM": 4,
            "FT-": "0",
            "PTS": 18,
            "OREB": "0",
            "REB": 6,
            "AST": 3,
            "ST": 0,
            "BLK": 0,
            "TO": 3,
            "TF": "0",
            "EJ": "0",
            "3D": "0",
            "2D": "0"
        },
        {
            "Date": "Mar 7",
            "Team": "NY",
            "Opp": "@LAC",
            "Score": "L 95-105",
            "FPts": 76,
            "FG-": "7.0",
            "3PTM": 1,
            "FT-": "1",
            "PTS": 14,
            "OREB": "2",
            "REB": 20,
            "AST": 6,
            "ST": 0,
            "BLK": 0,
            "TO": 2,
            "TF": "0",
            "EJ": "0",
            "3D": "0",
            "2D": "1"
        },
        {
            "Date": "Mar 6",
            "Team": "NY",
            "Opp": "@LAL",
            "Score": "L 109-113",
            "FPts": 78,
            "FG-": "7.0",
            "3PTM": 2,
            "FT-": "3",
            "PTS": 18,
            "OREB": "5",
            "REB": 10,
            "AST": 2,
            "ST": 4,
            "BLK": 0,
            "TO": 3,
            "TF": "0",
            "EJ": "0",
            "3D": "0",
            "2D": "1"
        },
        {
            "Date": "Mar 4",
            "Team": "NY",
            "Opp": "GS",
            "Score": "L 102-114",
            "FPts": 12,
            "FG-": "7.0",
            "3PTM": 0,
            "FT-": "0",
            "PTS": 2,
            "OREB": "1",
            "REB": 8,
            "AST": 3,
            "ST": 0,
            "BLK": 0,
            "TO": 2,
            "TF": "0",
            "EJ": "0",
            "3D": "0",
            "2D": "0"
        },
        {
            "Date": "Mar 2",
            "Team": "NY",
            "Opp": "@MIA",
            "Score": "W 116-112",
            "FPts": 43,
            "FG-": "5.0",
            "3PTM": 0,
            "FT-": "0",
            "PTS": 14,
            "OREB": "0",
            "REB": 7,
            "AST": 3,
            "ST": 0,
            "BLK": 1,
            "TO": 1,
            "TF": "0",
            "EJ": "0",
            "3D": "0",
            "2D": "0"
        },
        {
            "Date": "Feb 28",
            "Team": "NY",
            "Opp": "@MEM",
            "Score": "W 114-113",
            "FPts": 48,
            "FG-": "4.0",
            "3PTM": 1,
            "FT-": "1",
            "PTS": 12,
            "OREB": "0",
            "REB": 4,
            "AST": 6,
            "ST": 1,
            "BLK": 1,
            "TO": 3,
            "TF": "0",
            "EJ": "0",
            "3D": "0",
            "2D": "0"
        },
        {
            "Date": "Feb 26",
            "Team": "NY",
            "Opp": "PHI",
            "Score": "W 110-105",
            "FPts": 52,
            "FG-": "2.0",
            "3PTM": 0,
            "FT-": "3",
            "PTS": 7,
            "OREB": "3",
            "REB": 17,
            "AST": 4,
            "ST": 1,
            "BLK": 1,
            "TO": 7,
            "TF": "0",
            "EJ": "0",
            "3D": "0",
            "2D": "0"
        },
        {
            "Date": "Feb 23",
            "Team": "NY",
            "Opp": "@BOS",
            "Score": "L 105-118",
            "FPts": 79,
            "FG-": "6.0",
            "3PTM": 0,
            "FT-": "0",
            "PTS": 20,
            "OREB": "2",
            "REB": 11,
            "AST": 9,
            "ST": 0,
            "BLK": 0,
            "TO": 2,
            "TF": "0",
            "EJ": "0",
            "3D": "0",
            "2D": "1"
        },
        {
            "Date": "Feb 12",
            "Team": "NY",
            "Opp": "ATL",
            "Score": "W 149-148",
            "FPts": 69,
            "FG-": "8.0",
            "3PTM": 0,
            "FT-": "0",
            "PTS": 18,
            "OREB": "3",
            "REB": 10,
            "AST": 6,
            "ST": 1,
            "BLK": 1,
            "TO": 3,
            "TF": "0",
            "EJ": "0",
            "3D": "0",
            "2D": "1"
        },
        {
            "Date": "Feb 11",
            "Team": "NY",
            "Opp": "@IND",
            "Score": "W 128-115",
            "FPts": 100,
            "FG-": "4.0",
            "3PTM": 1,
            "FT-": "2",
            "PTS": 30,
            "OREB": "2",
            "REB": 10,
            "AST": 5,
            "ST": 2,
            "BLK": 0,
            "TO": 3,
            "TF": "0",
            "EJ": "0",
            "3D": "0",
            "2D": "1"
        },
        {
            "Date": "Feb 8",
            "Team": "NY",
            "Opp": "BOS",
            "Score": "L 104-131",
            "FPts": 49,
            "FG-": "9.0",
            "3PTM": 1,
            "FT-": "2",
            "PTS": 17,
            "OREB": "1",
            "REB": 8,
            "AST": 3,
            "ST": 2,
            "BLK": 0,
            "TO": 3,
            "TF": "0",
            "EJ": "0",
            "3D": "0",
            "2D": "0"
        },
        {
            "Date": "Feb 4",
            "Team": "NY",
            "Opp": "@TOR",
            "Score": "W 121-115",
            "FPts": 52,
            "FG-": "10.0",
            "3PTM": 1,
            "FT-": "0",
            "PTS": 15,
            "OREB": "1",
            "REB": 7,
            "AST": 6,
            "ST": 1,
            "BLK": 0,
            "TO": 0,
            "TF": "0",
            "EJ": "0",
            "3D": "0",
            "2D": "0"
        },
        {
            "Date": "Feb 3",
            "Team": "NY",
            "Opp": "HOU",
            "Score": "W 124-118",
            "FPts": 65,
            "FG-": "4.0",
            "3PTM": 0,
            "FT-": "0",
            "PTS": 19,
            "OREB": "2",
            "REB": 8,
            "AST": 5,
            "ST": 1,
            "BLK": 1,
            "TO": 4,
            "TF": "0",
            "EJ": "0",
            "3D": "0",
            "2D": "0"
        },
        {
            "Date": "Feb 1",
            "Team": "NY",
            "Opp": "LAL",
            "Score": "L 112-128",
            "FPts": 119,
            "FG-": "5.0",
            "3PTM": 1,
            "FT-": "1",
            "PTS": 26,
            "OREB": "4",
            "REB": 13,
            "AST": 11,
            "ST": 2,
            "BLK": 0,
            "TO": 2,
            "TF": "0",
            "EJ": "0",
            "3D": "1",
            "2D": "1"
        },
        {
            "Date": "Jan 29",
            "Team": "NY",
            "Opp": "DEN",
            "Score": "W 122-112",
            "FPts": 56,
            "FG-": "5.0",
            "3PTM": 0,
            "FT-": "1",
            "PTS": 15,
            "OREB": "0",
            "REB": 5,
            "AST": 5,
            "ST": 3,
            "BLK": 0,
            "TO": 0,
            "TF": "1",
            "EJ": "0",
            "3D": "0",
            "2D": "0"
        },
        {
            "Date": "Jan 27",
            "Team": "NY",
            "Opp": "MEM",
            "Score": "W 143-106",
            "FPts": 43,
            "FG-": "4.0",
            "3PTM": 0,
            "FT-": "0",
            "PTS": 4,
            "OREB": "2",
            "REB": 10,
            "AST": 5,
            "ST": 1,
            "BLK": 0,
            "TO": 0,
            "TF": "0",
            "EJ": "0",
            "3D": "0",
            "2D": "0"
        },
        {
            "Date": "Jan 25",
            "Team": "NY",
            "Opp": "SAC",
            "Score": "W 143-120",
            "FPts": 113,
            "FG-": "6.0",
            "3PTM": 1,
            "FT-": "0",
            "PTS": 20,
            "OREB": "7",
            "REB": 18,
            "AST": 11,
            "ST": 1,
            "BLK": 2,
            "TO": 3,
            "TF": "1",
            "EJ": "0",
            "3D": "1",
            "2D": "1"
        },
        {
            "Date": "Jan 21",
            "Team": "NY",
            "Opp": "@BKN",
            "Score": "W 99-95",
            "FPts": 73,
            "FG-": "2.0",
            "3PTM": 1,
            "FT-": "0",
            "PTS": 7,
            "OREB": "1",
            "REB": 12,
            "AST": 9,
            "ST": 2,
            "BLK": 0,
            "TO": 2,
            "TF": "0",
            "EJ": "0",
            "3D": "0",
            "2D": "0"
        },
        {
            "Date": "Jan 20",
            "Team": "NY",
            "Opp": "ATL",
            "Score": "W 119-110",
            "FPts": 63,
            "FG-": "5.0",
            "3PTM": 0,
            "FT-": "0",
            "PTS": 14,
            "OREB": "4",
            "REB": 9,
            "AST": 5,
            "ST": 2,
            "BLK": 0,
            "TO": 2,
            "TF": "0",
            "EJ": "0",
            "3D": "0",
            "2D": "0"
        },
        {
            "Date": "Jan 17",
            "Team": "NY",
            "Opp": "MIN",
            "Score": "L 99-116",
            "FPts": 40,
            "FG-": "9.0",
            "3PTM": 1,
            "FT-": "1",
            "PTS": 12,
            "OREB": "2",
            "REB": 9,
            "AST": 0,
            "ST": 3,
            "BLK": 0,
            "TO": 3,
            "TF": "0",
            "EJ": "0",
            "3D": "0",
            "2D": "0"
        },
        {
            "Date": "Jan 15",
            "Team": "NY",
            "Opp": "@PHI",
            "Score": "W 125-119",
            "FPts": 106,
            "FG-": "5.0",
            "3PTM": 0,
            "FT-": "1",
            "PTS": 10,
            "OREB": "5",
            "REB": 17,
            "AST": 12,
            "ST": 4,
            "BLK": 0,
            "TO": 3,
            "TF": "0",
            "EJ": "0",
            "3D": "1",
            "2D": "1"
        },
        {
            "Date": "Jan 13",
            "Team": "NY",
            "Opp": "DET",
            "Score": "L 119-124",
            "FPts": 70,
            "FG-": "2.0",
            "3PTM": 1,
            "FT-": "1",
            "PTS": 12,
            "OREB": "3",
            "REB": 14,
            "AST": 5,
            "ST": 0,
            "BLK": 0,
            "TO": 1,
            "TF": "0",
            "EJ": "0",
            "3D": "0",
            "2D": "1"
        },
        {
            "Date": "Jan 12",
            "Team": "NY",
            "Opp": "MIL",
            "Score": "W 140-106",
            "FPts": 65,
            "FG-": "0.0",
            "3PTM": 1,
            "FT-": "0",
            "PTS": 11,
            "OREB": "2",
            "REB": 11,
            "AST": 4,
            "ST": 1,
            "BLK": 0,
            "TO": 3,
            "TF": "0",
            "EJ": "0",
            "3D": "0",
            "2D": "1"
        },
        {
            "Date": "Jan 10",
            "Team": "NY",
            "Opp": "OKC",
            "Score": "L 101-126",
            "FPts": 76,
            "FG-": "7.0",
            "3PTM": 0,
            "FT-": "0",
            "PTS": 16,
            "OREB": "6",
            "REB": 13,
            "AST": 2,
            "ST": 3,
            "BLK": 0,
            "TO": 1,
            "TF": "0",
            "EJ": "0",
            "3D": "0",
            "2D": "1"
        },
        {
            "Date": "Jan 8",
            "Team": "NY",
            "Opp": "TOR",
            "Score": "W 112-98",
            "FPts": 94,
            "FG-": "5.0",
            "3PTM": 2,
            "FT-": "1",
            "PTS": 21,
            "OREB": "6",
            "REB": 11,
            "AST": 7,
            "ST": 1,
            "BLK": 0,
            "TO": 1,
            "TF": "0",
            "EJ": "0",
            "3D": "0",
            "2D": "1"
        },
        {
            "Date": "Jan 6",
            "Team": "NY",
            "Opp": "ORL",
            "Score": "L 94-103",
            "FPts": 80,
            "FG-": "4.0",
            "3PTM": 1,
            "FT-": "0",
            "PTS": 15,
            "OREB": "3",
            "REB": 14,
            "AST": 2,
            "ST": 2,
            "BLK": 1,
            "TO": 1,
            "TF": "0",
            "EJ": "0",
            "3D": "0",
            "2D": "1"
        },
        {
            "Date": "Jan 4",
            "Team": "NY",
            "Opp": "@CHI",
            "Score": "L 126-139",
            "FPts": 65,
            "FG-": "5.0",
            "3PTM": 0,
            "FT-": "0",
            "PTS": 2,
            "OREB": "3",
            "REB": 16,
            "AST": 10,
            "ST": 1,
            "BLK": 0,
            "TO": 2,
            "TF": "0",
            "EJ": "0",
            "3D": "0",
            "2D": "1"
        },
        {
            "Date": "Jan 3",
            "Team": "NY",
            "Opp": "@OKC",
            "Score": "L 107-117",
            "FPts": 52,
            "FG-": "7.0",
            "3PTM": 2,
            "FT-": "1",
            "PTS": 19,
            "OREB": "3",
            "REB": 7,
            "AST": 2,
            "ST": 1,
            "BLK": 1,
            "TO": 2,
            "TF": "1",
            "EJ": "0",
            "3D": "0",
            "2D": "0"
        },
        {
            "Date": "Jan 1",
            "Team": "NY",
            "Opp": "UTA",
            "Score": "W 119-103",
            "FPts": 86,
            "FG-": "6.0",
            "3PTM": 1,
            "FT-": "1",
            "PTS": 15,
            "OREB": "2",
            "REB": 14,
            "AST": 12,
            "ST": 1,
            "BLK": 1,
            "TO": 7,
            "TF": "0",
            "EJ": "0",
            "3D": "1",
            "2D": "1"
        },
        {
            "Date": "Dec 30",
            "Team": "NY",
            "Opp": "@WAS",
            "Score": "W 126-106",
            "FPts": 118,
            "FG-": "8.0",
            "3PTM": 4,
            "FT-": "2",
            "PTS": 23,
            "OREB": "4",
            "REB": 15,
            "AST": 10,
            "ST": 2,
            "BLK": 0,
            "TO": 1,
            "TF": "0",
            "EJ": "0",
            "3D": "1",
            "2D": "1"
        },
        {
            "Date": "Dec 28",
            "Team": "NY",
            "Opp": "@WAS",
            "Score": "W 136-132",
            "FPts": 68,
            "FG-": "5.0",
            "3PTM": 0,
            "FT-": "0",
            "PTS": 13,
            "OREB": "3",
            "REB": 11,
            "AST": 7,
            "ST": 1,
            "BLK": 0,
            "TO": 2,
            "TF": "0",
            "EJ": "0",
            "3D": "0",
            "2D": "1"
        },
        {
            "Date": "Dec 27",
            "Team": "NY",
            "Opp": "@ORL",
            "Score": "W 108-85",
            "FPts": 89,
            "FG-": "4.0",
            "3PTM": 1,
            "FT-": "2",
            "PTS": 23,
            "OREB": "3",
            "REB": 13,
            "AST": 1,
            "ST": 2,
            "BLK": 2,
            "TO": 3,
            "TF": "0",
            "EJ": "0",
            "3D": "0",
            "2D": "1"
        },
        {
            "Date": "Dec 25",
            "Team": "NY",
            "Opp": "SA",
            "Score": "W 117-114",
            "FPts": 79,
            "FG-": "4.0",
            "3PTM": 1,
            "FT-": "1",
            "PTS": 12,
            "OREB": "5",
            "REB": 12,
            "AST": 6,
            "ST": 2,
            "BLK": 0,
            "TO": 1,
            "TF": "0",
            "EJ": "0",
            "3D": "0",
            "2D": "1"
        },
        {
            "Date": "Dec 23",
            "Team": "NY",
            "Opp": "TOR",
            "Score": "W 139-125",
            "FPts": 25,
            "FG-": "3.0",
            "3PTM": 1,
            "FT-": "0",
            "PTS": 11,
            "OREB": "0",
            "REB": 3,
            "AST": 4,
            "ST": 0,
            "BLK": 0,
            "TO": 3,
            "TF": "1",
            "EJ": "0",
            "3D": "0",
            "2D": "0"
        },
        {
            "Date": "Dec 21",
            "Team": "NY",
            "Opp": "@NO",
            "Score": "W 104-93",
            "FPts": 62,
            "FG-": "7.0",
            "3PTM": 1,
            "FT-": "1",
            "PTS": 14,
            "OREB": "1",
            "REB": 8,
            "AST": 5,
            "ST": 2,
            "BLK": 1,
            "TO": 1,
            "TF": "0",
            "EJ": "0",
            "3D": "0",
            "2D": "0"
        },
        {
            "Date": "Dec 15",
            "Team": "NY",
            "Opp": "@ORL",
            "Score": "W 100-91",
            "FPts": 60,
            "FG-": "4.0",
            "3PTM": 1,
            "FT-": "2",
            "PTS": 12,
            "OREB": "0",
            "REB": 5,
            "AST": 5,
            "ST": 4,
            "BLK": 1,
            "TO": 5,
            "TF": "0",
            "EJ": "0",
            "3D": "0",
            "2D": "0"
        },
        {
            "Date": "Dec 11",
            "Team": "NY",
            "Opp": "ATL",
            "Score": "L 100-108",
            "FPts": 83,
            "FG-": "4.0",
            "3PTM": 3,
            "FT-": "0",
            "PTS": 21,
            "OREB": "2",
            "REB": 8,
            "AST": 6,
            "ST": 1,
            "BLK": 0,
            "TO": 1,
            "TF": "0",
            "EJ": "0",
            "3D": "0",
            "2D": "0"
        },
        {
            "Date": "Dec 9",
            "Team": "NY",
            "Opp": "@TOR",
            "Score": "W 113-108",
            "FPts": 36,
            "FG-": "5.0",
            "3PTM": 1,
            "FT-": "1",
            "PTS": 10,
            "OREB": "1",
            "REB": 4,
            "AST": 3,
            "ST": 1,
            "BLK": 0,
            "TO": 0,
            "TF": "0",
            "EJ": "0",
            "3D": "0",
            "2D": "0"
        },
        {
            "Date": "Dec 7",
            "Team": "NY",
            "Opp": "DET",
            "Score": "L 111-120",
            "FPts": 32,
            "FG-": "4.0",
            "3PTM": 1,
            "FT-": "1",
            "PTS": 17,
            "OREB": "1",
            "REB": 6,
            "AST": 3,
            "ST": 1,
            "BLK": 0,
            "TO": 0,
            "TF": "2",
            "EJ": "1",
            "3D": "0",
            "2D": "0"
        },
        {
            "Date": "Dec 5",
            "Team": "NY",
            "Opp": "CHA",
            "Score": "W 125-101",
            "FPts": 88,
            "FG-": "3.0",
            "3PTM": 4,
            "FT-": "0",
            "PTS": 18,
            "OREB": "0",
            "REB": 10,
            "AST": 6,
            "ST": 1,
            "BLK": 0,
            "TO": 1,
            "TF": "0",
            "EJ": "0",
            "3D": "0",
            "2D": "1"
        },
        {
            "Date": "Dec 3",
            "Team": "NY",
            "Opp": "ORL",
            "Score": "W 121-106",
            "FPts": 89,
            "FG-": "2.0",
            "3PTM": 0,
            "FT-": "0",
            "PTS": 11,
            "OREB": "1",
            "REB": 13,
            "AST": 10,
            "ST": 3,
            "BLK": 0,
            "TO": 4,
            "TF": "0",
            "EJ": "0",
            "3D": "1",
            "2D": "1"
        },
        {
            "Date": "Dec 1",
            "Team": "NY",
            "Opp": "NO",
            "Score": "W 118-85",
            "FPts": 60,
            "FG-": "4.0",
            "3PTM": 2,
            "FT-": "0",
            "PTS": 12,
            "OREB": "1",
            "REB": 6,
            "AST": 3,
            "ST": 2,
            "BLK": 1,
            "TO": 0,
            "TF": "0",
            "EJ": "0",
            "3D": "0",
            "2D": "0"
        },
        {
            "Date": "Nov 29",
            "Team": "NY",
            "Opp": "@CHA",
            "Score": "W 99-98",
            "FPts": 70,
            "FG-": "6.0",
            "3PTM": 1,
            "FT-": "0",
            "PTS": 13,
            "OREB": "4",
            "REB": 12,
            "AST": 5,
            "ST": 2,
            "BLK": 0,
            "TO": 3,
            "TF": "0",
            "EJ": "0",
            "3D": "0",
            "2D": "1"
        },
        {
            "Date": "Nov 27",
            "Team": "NY",
            "Opp": "@DAL",
            "Score": "L 114-129",
            "FPts": 53,
            "FG-": "5.0",
            "3PTM": 1,
            "FT-": "0",
            "PTS": 12,
            "OREB": "1",
            "REB": 2,
            "AST": 3,
            "ST": 4,
            "BLK": 0,
            "TO": 1,
            "TF": "0",
            "EJ": "0",
            "3D": "0",
            "2D": "0"
        },
        {
            "Date": "Nov 25",
            "Team": "NY",
            "Opp": "@DEN",
            "Score": "W 145-118",
            "FPts": 64,
            "FG-": "0.0",
            "3PTM": 1,
            "FT-": "0",
            "PTS": 12,
            "OREB": "2",
            "REB": 6,
            "AST": 5,
            "ST": 1,
            "BLK": 1,
            "TO": 1,
            "TF": "0",
            "EJ": "0",
            "3D": "0",
            "2D": "0"
        },
        {
            "Date": "Nov 23",
            "Team": "NY",
            "Opp": "@UTA",
            "Score": "L 106-121",
            "FPts": 78,
            "FG-": "5.0",
            "3PTM": 2,
            "FT-": "1",
            "PTS": 17,
            "OREB": "1",
            "REB": 6,
            "AST": 6,
            "ST": 2,
            "BLK": 3,
            "TO": 3,
            "TF": "0",
            "EJ": "0",
            "3D": "0",
            "2D": "0"
        },
        {
            "Date": "Nov 20",
            "Team": "NY",
            "Opp": "@PHO",
            "Score": "W 138-122",
            "FPts": 101,
            "FG-": "3.0",
            "3PTM": 2,
            "FT-": "1",
            "PTS": 19,
            "OREB": "4",
            "REB": 11,
            "AST": 6,
            "ST": 3,
            "BLK": 0,
            "TO": 1,
            "TF": "0",
            "EJ": "0",
            "3D": "0",
            "2D": "1"
        },
        {
            "Date": "Nov 18",
            "Team": "NY",
            "Opp": "WAS",
            "Score": "W 134-106",
            "FPts": 47,
            "FG-": "3.0",
            "3PTM": 2,
            "FT-": "0",
            "PTS": 14,
            "OREB": "0",
            "REB": 6,
            "AST": 3,
            "ST": 0,
            "BLK": 0,
            "TO": 1,
            "TF": "0",
            "EJ": "0",
            "3D": "0",
            "2D": "0"
        },
        {
            "Date": "Nov 17",
            "Team": "NY",
            "Opp": "BKN",
            "Score": "W 114-104",
            "FPts": 77,
            "FG-": "5.0",
            "3PTM": 3,
            "FT-": "0",
            "PTS": 20,
            "OREB": "0",
            "REB": 8,
            "AST": 8,
            "ST": 0,
            "BLK": 0,
            "TO": 1,
            "TF": "0",
            "EJ": "0",
            "3D": "0",
            "2D": "0"
        },
        {
            "Date": "Nov 15",
            "Team": "NY",
            "Opp": "BKN",
            "Score": "W 124-122",
            "FPts": 79,
            "FG-": "4.0",
            "3PTM": 2,
            "FT-": "0",
            "PTS": 14,
            "OREB": "0",
            "REB": 9,
            "AST": 9,
            "ST": 2,
            "BLK": 0,
            "TO": 2,
            "TF": "0",
            "EJ": "0",
            "3D": "0",
            "2D": "0"
        },
        {
            "Date": "Nov 13",
            "Team": "NY",
            "Opp": "CHI",
            "Score": "L 123-124",
            "FPts": 40,
            "FG-": "3.0",
            "3PTM": 0,
            "FT-": "0",
            "PTS": 6,
            "OREB": "4",
            "REB": 8,
            "AST": 6,
            "ST": 0,
            "BLK": 0,
            "TO": 2,
            "TF": "0",
            "EJ": "0",
            "3D": "0",
            "2D": "0"
        },
        {
            "Date": "Nov 12",
            "Team": "NY",
            "Opp": "@PHI",
            "Score": "W 111-99",
            "FPts": 88,
            "FG-": "2.0",
            "3PTM": 1,
            "FT-": "0",
            "PTS": 14,
            "OREB": "1",
            "REB": 12,
            "AST": 10,
            "ST": 1,
            "BLK": 1,
            "TO": 4,
            "TF": "0",
            "EJ": "0",
            "3D": "1",
            "2D": "1"
        },
        {
            "Date": "Nov 10",
            "Team": "NY",
            "Opp": "@IND",
            "Score": "L 121-132",
            "FPts": 73,
            "FG-": "5.0",
            "3PTM": 0,
            "FT-": "1",
            "PTS": 16,
            "OREB": "2",
            "REB": 10,
            "AST": 6,
            "ST": 1,
            "BLK": 1,
            "TO": 1,
            "TF": "0",
            "EJ": "0",
            "3D": "0",
            "2D": "1"
        },
        {
            "Date": "Nov 8",
            "Team": "NY",
            "Opp": "MIL",
            "Score": "W 116-94",
            "FPts": 64,
            "FG-": "1.0",
            "3PTM": 1,
            "FT-": "0",
            "PTS": 11,
            "OREB": "2",
            "REB": 9,
            "AST": 7,
            "ST": 0,
            "BLK": 0,
            "TO": 0,
            "TF": "0",
            "EJ": "0",
            "3D": "0",
            "2D": "0"
        },
        {
            "Date": "Nov 6",
            "Team": "NY",
            "Opp": "@ATL",
            "Score": "L 116-121",
            "FPts": 67,
            "FG-": "3.0",
            "3PTM": 2,
            "FT-": "0",
            "PTS": 14,
            "OREB": "1",
            "REB": 8,
            "AST": 8,
            "ST": 1,
            "BLK": 1,
            "TO": 3,
            "TF": "1",
            "EJ": "0",
            "3D": "0",
            "2D": "0"
        },
        {
            "Date": "Nov 4",
            "Team": "NY",
            "Opp": "@HOU",
            "Score": "L 97-109",
            "FPts": 41,
            "FG-": "5.0",
            "3PTM": 0,
            "FT-": "0",
            "PTS": 12,
            "OREB": "0",
            "REB": 4,
            "AST": 7,
            "ST": 1,
            "BLK": 0,
            "TO": 1,
            "TF": "1",
            "EJ": "0",
            "3D": "0",
            "2D": "0"
        },
        {
            "Date": "Nov 1",
            "Team": "NY",
            "Opp": "@DET",
            "Score": "W 128-98",
            "FPts": 62,
            "FG-": "3.0",
            "3PTM": 1,
            "FT-": "0",
            "PTS": 13,
            "OREB": "3",
            "REB": 9,
            "AST": 4,
            "ST": 2,
            "BLK": 0,
            "TO": 3,
            "TF": "0",
            "EJ": "0",
            "3D": "0",
            "2D": "0"
        },
        {
            "Date": "Oct 30",
            "Team": "NY",
            "Opp": "@MIA",
            "Score": "W 116-107",
            "FPts": 77,
            "FG-": "3.0",
            "3PTM": 2,
            "FT-": "0",
            "PTS": 10,
            "OREB": "1",
            "REB": 14,
            "AST": 6,
            "ST": 1,
            "BLK": 0,
            "TO": 0,
            "TF": "0",
            "EJ": "0",
            "3D": "0",
            "2D": "1"
        },
        {
            "Date": "Oct 28",
            "Team": "NY",
            "Opp": "CLE",
            "Score": "L 104-110",
            "FPts": 74,
            "FG-": "6.0",
            "3PTM": 2,
            "FT-": "0",
            "PTS": 16,
            "OREB": "4",
            "REB": 13,
            "AST": 2,
            "ST": 3,
            "BLK": 0,
            "TO": 5,
            "TF": "0",
            "EJ": "0",
            "3D": "0",
            "2D": "1"
        },
        {
            "Date": "Oct 25",
            "Team": "NY",
            "Opp": "IND",
            "Score": "W 123-98",
            "FPts": 64,
            "FG-": "7.0",
            "3PTM": 1,
            "FT-": "1",
            "PTS": 20,
            "OREB": "3",
            "REB": 10,
            "AST": 3,
            "ST": 1,
            "BLK": 0,
            "TO": 3,
            "TF": "0",
            "EJ": "0",
            "3D": "0",
            "2D": "1"
        },
        {
            "Date": "Oct 22",
            "Team": "NY",
            "Opp": "@BOS",
            "Score": "L 109-132",
            "FPts": 34,
            "FG-": "2.0",
            "3PTM": 0,
            "FT-": "2",
            "PTS": 12,
            "OREB": "1",
            "REB": 4,
            "AST": 3,
            "ST": 0,
            "BLK": 0,
            "TO": 1,
            "TF": "0",
            "EJ": "0",
            "3D": "0",
            "2D": "0"
        }
    ],
    "status": "success"
}